{
  "config": {
    "startDate": "2024-01-01",
    "endDate": "2024-12-31",
    "positionSize": 10000,
    "maxDailyTrades": 5,
    "minScore": 50,
    "minGapPercent": 5,
    "maxGapPercent": 100,
    "minPrice": 1,
    "maxPrice": 20,
    "maxFloat": 50000000,
    "largeCapsOnly": false,
    "delayedEntry": true
  },
  "trades": [
    {
      "symbol": "SASI",
      "date": "2024-01-03",
      "entryTime": "2024-01-03T14:44:00.000Z",
      "entryPrice": 4.72,
      "stopLoss": 4.19,
      "target1": 5.7799999999999985,
      "target2": 6.309999999999998,
      "riskRewardRatio": "1:2",
      "positionSize": 1779.4399999999998,
      "status": "closed",
      "exitTime": "2024-01-03T15:22:00.000Z",
      "exitPrice": 4.19,
      "exitReason": "stop_loss",
      "pnl": -199.80999999999975,
      "pnlPercent": -11.22881355932202
    },
    {
      "symbol": "UK",
      "date": "2024-01-03",
      "entryTime": "2024-01-03T14:53:00.000Z",
      "entryPrice": 5.2,
      "stopLoss": 4.49,
      "target1": 6.62,
      "target2": 7.33,
      "riskRewardRatio": "1:2",
      "positionSize": 1461.2,
      "status": "closed",
      "exitTime": "2024-01-03T18:45:00.000Z",
      "exitPrice": 4.49,
      "exitReason": "stop_loss",
      "pnl": -199.51,
      "pnlPercent": -13.653846153846153
    },
    {
      "symbol": "OMGA",
      "date": "2024-01-04",
      "entryTime": "2024-01-04T14:44:00.000Z",
      "entryPrice": 5.41,
      "stopLoss": 3.55,
      "target1": 9.13,
      "target2": 10.990000000000002,
      "riskRewardRatio": "1:2",
      "positionSize": 578.87,
      "status": "closed",
      "exitTime": "2024-01-04T20:59:00.000Z",
      "exitPrice": 5.3199,
      "exitReason": "end_of_day",
      "pnl": -9.640700000000056,
      "pnlPercent": -1.6654343807763496
    },
    {
      "symbol": "CYCC",
      "date": "2024-01-08",
      "entryTime": "2024-01-08T14:44:00.000Z",
      "entryPrice": 2.7299,
      "stopLoss": 2.45,
      "target1": 3.2897000000000003,
      "target2": 3.5696000000000003,
      "riskRewardRatio": "1:2",
      "positionSize": 1949.1486000000002,
      "status": "closed",
      "exitTime": "2024-01-08T20:59:00.000Z",
      "exitPrice": 3.2,
      "exitReason": "end_of_day",
      "pnl": 335.65139999999997,
      "pnlPercent": 17.22041100406608
    },
    {
      "symbol": "TPET",
      "date": "2024-01-11",
      "entryTime": "2024-01-11T14:51:00.000Z",
      "entryPrice": 5.442,
      "stopLoss": 5.14,
      "target1": 6.046000000000001,
      "target2": 6.348000000000002,
      "riskRewardRatio": "1:2",
      "positionSize": 3602.6040000000003,
      "status": "closed",
      "exitTime": "2024-01-11T20:59:00.000Z",
      "exitPrice": 5.202,
      "exitReason": "end_of_day",
      "pnl": -158.88000000000014,
      "pnlPercent": -4.410143329658218
    },
    {
      "symbol": "BFRG",
      "date": "2024-01-17",
      "entryTime": "2024-01-17T14:44:00.000Z",
      "entryPrice": 3.37,
      "stopLoss": 2.78,
      "target1": 4.550000000000001,
      "target2": 5.140000000000001,
      "riskRewardRatio": "1:2",
      "positionSize": 1139.06,
      "status": "closed",
      "exitTime": "2024-01-17T20:59:00.000Z",
      "exitPrice": 3.185,
      "exitReason": "end_of_day",
      "pnl": -62.530000000000015,
      "pnlPercent": -5.489614243323444
    },
    {
      "symbol": "BDRY",
      "date": "2024-01-18",
      "entryTime": "2024-01-18T14:47:00.000Z",
      "entryPrice": 11.1,
      "stopLoss": 10.06,
      "target1": 13.179999999999998,
      "target2": 14.219999999999997,
      "riskRewardRatio": "1:2",
      "positionSize": 2131.2,
      "status": "closed",
      "exitTime": "2024-01-18T20:59:00.000Z",
      "exitPrice": 11.15,
      "exitReason": "end_of_day",
      "pnl": 9.600000000000136,
      "pnlPercent": 0.45045045045045684
    },
    {
      "symbol": "SZZL",
      "date": "2024-01-29",
      "entryTime": "2024-01-29T15:56:00.000Z",
      "entryPrice": 11.02,
      "stopLoss": 10.55,
      "target1": 11.959999999999997,
      "target2": 12.429999999999996,
      "riskRewardRatio": "1:2",
      "positionSize": 4683.5,
      "status": "closed",
      "exitTime": "2024-01-29T20:27:00.000Z",
      "exitPrice": 11.03,
      "exitReason": "end_of_day",
      "pnl": 4.249999999999909,
      "pnlPercent": 0.0907441016333919
    },
    {
      "symbol": "CMMB",
      "date": "2024-01-30",
      "entryTime": "2024-01-30T15:22:00.000Z",
      "entryPrice": 2.32,
      "stopLoss": 2.2,
      "target1": 2.559999999999999,
      "target2": 2.679999999999999,
      "riskRewardRatio": "1:2",
      "positionSize": 3865.12,
      "status": "closed",
      "exitTime": "2024-01-30T20:58:00.000Z",
      "exitPrice": 2.32,
      "exitReason": "end_of_day",
      "pnl": 0,
      "pnlPercent": 0
    },
    {
      "symbol": "NRBO",
      "date": "2024-02-01",
      "entryTime": "2024-02-01T14:44:00.000Z",
      "entryPrice": 5.0822,
      "stopLoss": 3.26,
      "target1": 8.726600000000001,
      "target2": 10.548800000000002,
      "riskRewardRatio": "1:2",
      "positionSize": 553.9598000000001,
      "status": "closed",
      "exitTime": "2024-02-01T20:59:00.000Z",
      "exitPrice": 5.46,
      "exitReason": "end_of_day",
      "pnl": 41.180199999999964,
      "pnlPercent": 7.433788516784063
    },
    {
      "symbol": "NVDX",
      "date": "2024-02-05",
      "entryTime": "2024-02-05T14:44:00.000Z",
      "entryPrice": 6.215,
      "stopLoss": 5.86,
      "target1": 6.924999999999999,
      "target2": 7.2799999999999985,
      "riskRewardRatio": "1:2",
      "positionSize": 3499.045,
      "status": "closed",
      "exitTime": "2024-02-05T20:59:00.000Z",
      "exitPrice": 6.297,
      "exitReason": "end_of_day",
      "pnl": 46.16599999999992,
      "pnlPercent": 1.3193885760257418
    },
    {
      "symbol": "BDRY",
      "date": "2024-02-05",
      "entryTime": "2024-02-05T14:47:00.000Z",
      "entryPrice": 11.89,
      "stopLoss": 11.54,
      "target1": 12.590000000000003,
      "target2": 12.940000000000005,
      "riskRewardRatio": "1:2",
      "positionSize": 6789.1900000000005,
      "status": "closed",
      "exitTime": "2024-02-05T20:59:00.000Z",
      "exitPrice": 11.81,
      "exitReason": "end_of_day",
      "pnl": -45.68000000000004,
      "pnlPercent": -0.6728343145500426
    },
    {
      "symbol": "AGFY",
      "date": "2024-02-06",
      "entryTime": "2024-02-06T14:44:00.000Z",
      "entryPrice": 13.7625,
      "stopLoss": 9.0525,
      "target1": 23.182499999999997,
      "target2": 27.8925,
      "riskRewardRatio": "1:2",
      "positionSize": 578.025,
      "status": "closed",
      "exitTime": "2024-02-06T20:59:00.000Z",
      "exitPrice": 11.7,
      "exitReason": "end_of_day",
      "pnl": -86.625,
      "pnlPercent": -14.986376021798367
    },
    {
      "symbol": "GRDI",
      "date": "2024-02-07",
      "entryTime": "2024-02-07T14:44:00.000Z",
      "entryPrice": 2.424,
      "stopLoss": 2.21,
      "target1": 2.852,
      "target2": 3.066,
      "riskRewardRatio": "1:2",
      "positionSize": 2264.016,
      "status": "closed",
      "exitTime": "2024-02-07T15:48:00.000Z",
      "exitPrice": 2.21,
      "exitReason": "stop_loss",
      "pnl": -199.87599999999998,
      "pnlPercent": -8.828382838283828
    },
    {
      "symbol": "LIAN",
      "date": "2024-02-13",
      "entryTime": "2024-02-13T14:44:00.000Z",
      "entryPrice": 4.7688,
      "stopLoss": 4.15,
      "target1": 6.006399999999998,
      "target2": 6.625199999999998,
      "riskRewardRatio": "1:2",
      "positionSize": 1540.3224,
      "status": "closed",
      "exitTime": "2024-02-13T20:59:00.000Z",
      "exitPrice": 4.795,
      "exitReason": "end_of_day",
      "pnl": 8.462600000000073,
      "pnlPercent": 0.5494044623385385
    },
    {
      "symbol": "SOUNW",
      "date": "2024-02-21",
      "entryTime": "2024-02-21T14:44:00.000Z",
      "entryPrice": 2.75,
      "stopLoss": 2.03,
      "target1": 4.19,
      "target2": 4.91,
      "riskRewardRatio": "1:2",
      "positionSize": 761.75,
      "status": "closed",
      "exitTime": "2024-02-21T16:34:00.000Z",
      "exitPrice": 2.03,
      "exitReason": "stop_loss",
      "pnl": -199.44000000000005,
      "pnlPercent": -26.18181818181819
    },
    {
      "symbol": "EVGN",
      "date": "2024-02-21",
      "entryTime": "2024-02-21T14:44:00.000Z",
      "entryPrice": 8.91,
      "stopLoss": 7.927,
      "target1": 10.876000000000001,
      "target2": 11.859000000000002,
      "riskRewardRatio": "1:2",
      "positionSize": 1808.73,
      "status": "closed",
      "exitTime": "2024-02-21T20:59:00.000Z",
      "exitPrice": 9.3,
      "exitReason": "end_of_day",
      "pnl": 79.17000000000012,
      "pnlPercent": 4.377104377104383
    },
    {
      "symbol": "YINN",
      "date": "2024-02-21",
      "entryTime": "2024-02-21T14:44:00.000Z",
      "entryPrice": 18.7201,
      "stopLoss": 18.3,
      "target1": 19.560299999999994,
      "target2": 19.980399999999992,
      "riskRewardRatio": "1:2",
      "positionSize": 8910.7676,
      "status": "closed",
      "exitTime": "2024-02-21T20:12:00.000Z",
      "exitPrice": 18.3,
      "exitReason": "stop_loss",
      "pnl": -199.967599999999,
      "pnlPercent": -2.2441119438464425
    },
    {
      "symbol": "ROOT",
      "date": "2024-02-22",
      "entryTime": "2024-02-22T14:44:00.000Z",
      "entryPrice": 12.1,
      "stopLoss": 10.28,
      "target1": 15.74,
      "target2": 17.560000000000002,
      "riskRewardRatio": "1:2",
      "positionSize": 1318.8999999999999,
      "status": "closed",
      "exitTime": "2024-02-22T20:59:00.000Z",
      "exitPrice": 13.3,
      "exitReason": "end_of_day",
      "pnl": 130.80000000000013,
      "pnlPercent": 9.917355371900834
    },
    {
      "symbol": "RCM",
      "date": "2024-02-26",
      "entryTime": "2024-02-26T14:44:00.000Z",
      "entryPrice": 14.08,
      "stopLoss": 11.37,
      "target1": 19.5,
      "target2": 22.21,
      "riskRewardRatio": "1:2",
      "positionSize": 1027.84,
      "status": "closed",
      "exitTime": "2024-02-26T20:59:00.000Z",
      "exitPrice": 13.88,
      "exitReason": "end_of_day",
      "pnl": -14.599999999999948,
      "pnlPercent": -1.4204545454545403
    },
    {
      "symbol": "IVDA",
      "date": "2024-02-26",
      "entryTime": "2024-02-26T14:49:00.000Z",
      "entryPrice": 8.2376,
      "stopLoss": 7.52,
      "target1": 9.672800000000002,
      "target2": 10.390400000000003,
      "riskRewardRatio": "1:2",
      "positionSize": 2290.0528,
      "status": "closed",
      "exitTime": "2024-02-26T20:59:00.000Z",
      "exitPrice": 7.9192,
      "exitReason": "end_of_day",
      "pnl": -88.51520000000014,
      "pnlPercent": -3.865203457317671
    },
    {
      "symbol": "NUKK",
      "date": "2024-02-28",
      "entryTime": "2024-02-28T14:48:00.000Z",
      "entryPrice": 8.4792,
      "stopLoss": 7.6,
      "target1": 10.237600000000002,
      "target2": 11.116800000000003,
      "riskRewardRatio": "1:2",
      "positionSize": 1924.7784000000001,
      "status": "closed",
      "exitTime": "2024-02-28T20:59:00.000Z",
      "exitPrice": 7.7488,
      "exitReason": "end_of_day",
      "pnl": -165.8008000000001,
      "pnlPercent": -8.614020190584021
    },
    {
      "symbol": "PHUN",
      "date": "2024-03-05",
      "entryTime": "2024-03-05T14:44:00.000Z",
      "entryPrice": 16.2789,
      "stopLoss": 14.5,
      "target1": 19.8367,
      "target2": 21.6156,
      "riskRewardRatio": "1:2",
      "positionSize": 1823.2368000000001,
      "status": "closed",
      "exitTime": "2024-03-05T14:59:00.000Z",
      "exitPrice": 14.5,
      "exitReason": "stop_loss",
      "pnl": -199.23680000000002,
      "pnlPercent": -10.927642531129255
    },
    {
      "symbol": "NKGN",
      "date": "2024-03-06",
      "entryTime": "2024-03-06T14:44:00.000Z",
      "entryPrice": 1.32,
      "stopLoss": 1.15,
      "target1": 1.6600000000000004,
      "target2": 1.8300000000000005,
      "riskRewardRatio": "1:2",
      "positionSize": 1552.3200000000002,
      "status": "closed",
      "exitTime": "2024-03-06T15:19:00.000Z",
      "exitPrice": 1.6600000000000004,
      "exitReason": "target1",
      "pnl": 399.8400000000004,
      "pnlPercent": 25.75757575757578
    },
    {
      "symbol": "DADA",
      "date": "2024-03-06",
      "entryTime": "2024-03-06T14:44:00.000Z",
      "entryPrice": 2.775,
      "stopLoss": 2.13,
      "target1": 4.0649999999999995,
      "target2": 4.71,
      "riskRewardRatio": "1:2",
      "positionSize": 860.25,
      "status": "closed",
      "exitTime": "2024-03-06T20:59:00.000Z",
      "exitPrice": 2.57,
      "exitReason": "end_of_day",
      "pnl": -63.550000000000026,
      "pnlPercent": -7.38738738738739
    },
    {
      "symbol": "YINN",
      "date": "2024-03-06",
      "entryTime": "2024-03-06T14:44:00.000Z",
      "entryPrice": 18.5723,
      "stopLoss": 17.9,
      "target1": 19.9169,
      "target2": 20.589199999999998,
      "riskRewardRatio": "1:2",
      "positionSize": 5515.973099999999,
      "status": "closed",
      "exitTime": "2024-03-06T20:59:00.000Z",
      "exitPrice": 18.18,
      "exitReason": "end_of_day",
      "pnl": -116.51309999999964,
      "pnlPercent": -2.112285500449588
    },
    {
      "symbol": "SWBI",
      "date": "2024-03-08",
      "entryTime": "2024-03-08T14:44:00.000Z",
      "entryPrice": 16.4,
      "stopLoss": 14.15,
      "target1": 20.899999999999995,
      "target2": 23.14999999999999,
      "riskRewardRatio": "1:2",
      "positionSize": 1443.1999999999998,
      "status": "closed",
      "exitTime": "2024-03-08T20:59:00.000Z",
      "exitPrice": 17.39,
      "exitReason": "end_of_day",
      "pnl": 87.12000000000018,
      "pnlPercent": 6.0365853658536714
    },
    {
      "symbol": "YINN",
      "date": "2024-03-11",
      "entryTime": "2024-03-11T14:44:00.000Z",
      "entryPrice": 19.285,
      "stopLoss": 18.54,
      "target1": 20.775000000000002,
      "target2": 21.520000000000003,
      "riskRewardRatio": "1:2",
      "positionSize": 5168.38,
      "status": "closed",
      "exitTime": "2024-03-11T20:56:00.000Z",
      "exitPrice": 19.23,
      "exitReason": "end_of_day",
      "pnl": -14.739999999999924,
      "pnlPercent": -0.2851957479906648
    },
    {
      "symbol": "SGLY",
      "date": "2024-03-12",
      "entryTime": "2024-03-12T14:48:00.000Z",
      "entryPrice": 5.95,
      "stopLoss": 3.76,
      "target1": 10.330000000000002,
      "target2": 12.520000000000001,
      "riskRewardRatio": "1:2",
      "positionSize": 541.45,
      "status": "closed",
      "exitTime": "2024-03-12T20:56:00.000Z",
      "exitPrice": 4.79,
      "exitReason": "end_of_day",
      "pnl": -105.56000000000002,
      "pnlPercent": -19.495798319327733
    },
    {
      "symbol": "AISP",
      "date": "2024-03-12",
      "entryTime": "2024-03-12T14:44:00.000Z",
      "entryPrice": 7.2715,
      "stopLoss": 6.84,
      "target1": 8.1345,
      "target2": 8.565999999999999,
      "riskRewardRatio": "1:2",
      "positionSize": 3366.7045,
      "status": "closed",
      "exitTime": "2024-03-12T20:59:00.000Z",
      "exitPrice": 7.57,
      "exitReason": "end_of_day",
      "pnl": 138.2055000000003,
      "pnlPercent": 4.105067730179477
    },
    {
      "symbol": "ARQ",
      "date": "2024-03-13",
      "entryTime": "2024-03-13T14:44:00.000Z",
      "entryPrice": 4.5463,
      "stopLoss": 3.66,
      "target1": 6.318899999999998,
      "target2": 7.205199999999998,
      "riskRewardRatio": "1:2",
      "positionSize": 1022.9174999999999,
      "status": "closed",
      "exitTime": "2024-03-13T20:40:00.000Z",
      "exitPrice": 5.03,
      "exitReason": "end_of_day",
      "pnl": 108.83250000000015,
      "pnlPercent": 10.639421067681427
    },
    {
      "symbol": "BTMD",
      "date": "2024-03-13",
      "entryTime": "2024-03-13T15:02:00.000Z",
      "entryPrice": 6.55,
      "stopLoss": 5.8322,
      "target1": 7.985599999999999,
      "target2": 8.703399999999998,
      "riskRewardRatio": "1:2",
      "positionSize": 1820.8999999999999,
      "status": "closed",
      "exitTime": "2024-03-13T19:59:00.000Z",
      "exitPrice": 6.15,
      "exitReason": "end_of_day",
      "pnl": -111.19999999999985,
      "pnlPercent": -6.106870229007626
    },
    {
      "symbol": "RGLS",
      "date": "2024-03-13",
      "entryTime": "2024-03-13T14:44:00.000Z",
      "entryPrice": 2.498,
      "stopLoss": 2.23,
      "target1": 3.0340000000000007,
      "target2": 3.302000000000001,
      "riskRewardRatio": "1:2",
      "positionSize": 1863.5080000000003,
      "status": "closed",
      "exitTime": "2024-03-13T20:59:00.000Z",
      "exitPrice": 2.46,
      "exitReason": "end_of_day",
      "pnl": -28.34800000000019,
      "pnlPercent": -1.5212169735788732
    },
    {
      "symbol": "ASLE",
      "date": "2024-03-14",
      "entryTime": "2024-03-14T14:50:00.000Z",
      "entryPrice": 7.3601,
      "stopLoss": 7.05,
      "target1": 7.980300000000001,
      "target2": 8.290400000000002,
      "riskRewardRatio": "1:2",
      "positionSize": 4739.9044,
      "status": "closed",
      "exitTime": "2024-03-14T20:00:00.000Z",
      "exitPrice": 7.23,
      "exitReason": "end_of_day",
      "pnl": -83.78439999999978,
      "pnlPercent": -1.767639026643655
    },
    {
      "symbol": "XTLB",
      "date": "2024-03-18",
      "entryTime": "2024-03-18T19:29:00.000Z",
      "entryPrice": 4.3216,
      "stopLoss": 3.9556,
      "target1": 5.0536,
      "target2": 5.419600000000001,
      "riskRewardRatio": "1:2",
      "positionSize": 2359.5936,
      "status": "closed",
      "exitTime": "2024-03-18T20:13:00.000Z",
      "exitPrice": 4.52,
      "exitReason": "end_of_day",
      "pnl": 108.32639999999971,
      "pnlPercent": 4.590892262125126
    },
    {
      "symbol": "IVDA",
      "date": "2024-03-19",
      "entryTime": "2024-03-19T15:49:00.000Z",
      "entryPrice": 6.24,
      "stopLoss": 5.6536,
      "target1": 7.412800000000001,
      "target2": 7.999200000000001,
      "riskRewardRatio": "1:2",
      "positionSize": 2127.84,
      "status": "closed",
      "exitTime": "2024-03-19T20:23:00.000Z",
      "exitPrice": 6.7184,
      "exitReason": "end_of_day",
      "pnl": 163.1343999999999,
      "pnlPercent": 7.666666666666662
    },
    {
      "symbol": "IVDA",
      "date": "2024-03-20",
      "entryTime": "2024-03-20T15:12:00.000Z",
      "entryPrice": 7.2008,
      "stopLoss": 6.6,
      "target1": 8.4024,
      "target2": 9.003200000000001,
      "riskRewardRatio": "1:2",
      "positionSize": 2390.6656,
      "status": "closed",
      "exitTime": "2024-03-20T16:10:00.000Z",
      "exitPrice": 6.6,
      "exitReason": "stop_loss",
      "pnl": -199.46560000000014,
      "pnlPercent": -8.34351738695701
    },
    {
      "symbol": "SHOT",
      "date": "2024-03-20",
      "entryTime": "2024-03-20T14:44:00.000Z",
      "entryPrice": 2.81,
      "stopLoss": 2.56,
      "target1": 3.31,
      "target2": 3.56,
      "riskRewardRatio": "1:2",
      "positionSize": 2248,
      "status": "closed",
      "exitTime": "2024-03-20T20:38:00.000Z",
      "exitPrice": 2.66,
      "exitReason": "end_of_day",
      "pnl": -119.99999999999993,
      "pnlPercent": -5.338078291814943
    },
    {
      "symbol": "NYXH",
      "date": "2024-03-21",
      "entryTime": "2024-03-21T15:34:00.000Z",
      "entryPrice": 15.595,
      "stopLoss": 14.89,
      "target1": 17.005000000000003,
      "target2": 17.71,
      "riskRewardRatio": "1:2",
      "positionSize": 4413.385,
      "status": "closed",
      "exitTime": "2024-03-21T17:39:00.000Z",
      "exitPrice": 14.89,
      "exitReason": "stop_loss",
      "pnl": -199.51500000000001,
      "pnlPercent": -4.520679705033666
    },
    {
      "symbol": "FRSX",
      "date": "2024-03-22",
      "entryTime": "2024-03-22T14:44:00.000Z",
      "entryPrice": 7.98,
      "stopLoss": 7.07,
      "target1": 9.8,
      "target2": 10.71,
      "riskRewardRatio": "1:2",
      "positionSize": 1747.6200000000001,
      "status": "closed",
      "exitTime": "2024-03-22T20:58:00.000Z",
      "exitPrice": 7.91,
      "exitReason": "end_of_day",
      "pnl": -15.330000000000062,
      "pnlPercent": -0.877192982456144
    },
    {
      "symbol": "NTRB",
      "date": "2024-03-22",
      "entryTime": "2024-03-22T15:19:00.000Z",
      "entryPrice": 2.66,
      "stopLoss": 2.48,
      "target1": 3.0200000000000005,
      "target2": 3.2000000000000006,
      "riskRewardRatio": "1:2",
      "positionSize": 2955.26,
      "status": "closed",
      "exitTime": "2024-03-22T19:59:00.000Z",
      "exitPrice": 2.69,
      "exitReason": "end_of_day",
      "pnl": 33.329999999999785,
      "pnlPercent": 1.1278195488721732
    },
    {
      "symbol": "KULR",
      "date": "2024-03-25",
      "entryTime": "2024-03-25T14:44:00.000Z",
      "entryPrice": 2.5304,
      "stopLoss": 1.676,
      "target1": 4.2392,
      "target2": 5.093600000000001,
      "riskRewardRatio": "1:2",
      "positionSize": 592.1136,
      "status": "closed",
      "exitTime": "2024-03-25T20:59:00.000Z",
      "exitPrice": 2.5344,
      "exitReason": "end_of_day",
      "pnl": 0.9360000000000008,
      "pnlPercent": 0.15807777426493846
    },
    {
      "symbol": "DTSS",
      "date": "2024-03-26",
      "entryTime": "2024-03-26T14:47:00.000Z",
      "entryPrice": 7.58,
      "stopLoss": 6.82,
      "target1": 9.1,
      "target2": 9.86,
      "riskRewardRatio": "1:2",
      "positionSize": 1993.54,
      "status": "closed",
      "exitTime": "2024-03-26T19:59:00.000Z",
      "exitPrice": 7.6,
      "exitReason": "end_of_day",
      "pnl": 5.259999999999888,
      "pnlPercent": 0.26385224274405766
    },
    {
      "symbol": "TSLT",
      "date": "2024-03-26",
      "entryTime": "2024-03-26T14:44:00.000Z",
      "entryPrice": 12.09,
      "stopLoss": 11.03,
      "target1": 14.21,
      "target2": 15.270000000000001,
      "riskRewardRatio": "1:2",
      "positionSize": 2272.92,
      "status": "closed",
      "exitTime": "2024-03-26T20:59:00.000Z",
      "exitPrice": 11.56,
      "exitReason": "end_of_day",
      "pnl": -99.63999999999987,
      "pnlPercent": -4.383788254755991
    },
    {
      "symbol": "LIXT",
      "date": "2024-03-27",
      "entryTime": "2024-03-27T14:44:00.000Z",
      "entryPrice": 3.55,
      "stopLoss": 2.55,
      "target1": 5.55,
      "target2": 6.55,
      "riskRewardRatio": "1:2",
      "positionSize": 710,
      "status": "closed",
      "exitTime": "2024-03-27T20:58:00.000Z",
      "exitPrice": 3.48,
      "exitReason": "end_of_day",
      "pnl": -13.999999999999968,
      "pnlPercent": -1.9718309859154886
    },
    {
      "symbol": "REBN",
      "date": "2024-03-28",
      "entryTime": "2024-03-28T15:09:00.000Z",
      "entryPrice": 1.24,
      "stopLoss": 1.01,
      "target1": 1.7,
      "target2": 1.93,
      "riskRewardRatio": "1:2",
      "positionSize": 1077.56,
      "status": "closed",
      "exitTime": "2024-03-28T20:41:00.000Z",
      "exitPrice": 1.2,
      "exitReason": "end_of_day",
      "pnl": -34.76000000000003,
      "pnlPercent": -3.2258064516129057
    },
    {
      "symbol": "TPET",
      "date": "2024-04-02",
      "entryTime": "2024-04-02T14:44:00.000Z",
      "entryPrice": 3.444,
      "stopLoss": 2.302,
      "target1": 5.728,
      "target2": 6.869999999999999,
      "riskRewardRatio": "1:2",
      "positionSize": 602.7,
      "status": "closed",
      "exitTime": "2024-04-02T20:59:00.000Z",
      "exitPrice": 2.576,
      "exitReason": "end_of_day",
      "pnl": -151.89999999999998,
      "pnlPercent": -25.203252032520325
    },
    {
      "symbol": "QTTB",
      "date": "2024-04-02",
      "entryTime": "2024-04-02T14:52:00.000Z",
      "entryPrice": 21,
      "stopLoss": 18.855,
      "target1": 25.29,
      "target2": 27.435,
      "riskRewardRatio": "1:2",
      "positionSize": 1953,
      "status": "closed",
      "exitTime": "2024-04-02T19:59:00.000Z",
      "exitPrice": 21.98,
      "exitReason": "end_of_day",
      "pnl": 91.14000000000004,
      "pnlPercent": 4.666666666666669
    },
    {
      "symbol": "VSTE",
      "date": "2024-04-04",
      "entryTime": "2024-04-04T14:49:00.000Z",
      "entryPrice": 8.7,
      "stopLoss": 7.08,
      "target1": 11.939999999999998,
      "target2": 13.559999999999997,
      "riskRewardRatio": "1:2",
      "positionSize": 1070.1,
      "status": "closed",
      "exitTime": "2024-04-04T19:54:00.000Z",
      "exitPrice": 7.08,
      "exitReason": "stop_loss",
      "pnl": -199.2599999999999,
      "pnlPercent": -18.620689655172406
    },
    {
      "symbol": "NOTE",
      "date": "2024-04-04",
      "entryTime": "2024-04-04T14:53:00.000Z",
      "entryPrice": 15.6,
      "stopLoss": 14.04,
      "target1": 18.72,
      "target2": 20.28,
      "riskRewardRatio": "1:2",
      "positionSize": 1996.8,
      "status": "closed",
      "exitTime": "2024-04-04T20:06:00.000Z",
      "exitPrice": 15.84,
      "exitReason": "end_of_day",
      "pnl": 30.720000000000027,
      "pnlPercent": 1.5384615384615399
    },
    {
      "symbol": "ANGH",
      "date": "2024-04-09",
      "entryTime": "2024-04-09T14:44:00.000Z",
      "entryPrice": 13.5,
      "stopLoss": 11.3,
      "target1": 17.9,
      "target2": 20.099999999999998,
      "riskRewardRatio": "1:2",
      "positionSize": 1215,
      "status": "closed",
      "exitTime": "2024-04-09T20:58:00.000Z",
      "exitPrice": 12.9,
      "exitReason": "end_of_day",
      "pnl": -53.99999999999997,
      "pnlPercent": -4.444444444444442
    },
    {
      "symbol": "ADIL",
      "date": "2024-04-10",
      "entryTime": "2024-04-10T14:44:00.000Z",
      "entryPrice": 2.01,
      "stopLoss": 1.09,
      "target1": 3.849999999999999,
      "target2": 4.769999999999999,
      "riskRewardRatio": "1:2",
      "positionSize": 436.16999999999996,
      "status": "closed",
      "exitTime": "2024-04-10T20:59:00.000Z",
      "exitPrice": 2.5,
      "exitReason": "end_of_day",
      "pnl": 106.33000000000004,
      "pnlPercent": 24.378109452736332
    },
    {
      "symbol": "IMRN",
      "date": "2024-04-10",
      "entryTime": "2024-04-10T15:26:00.000Z",
      "entryPrice": 3.0246,
      "stopLoss": 2.82,
      "target1": 3.4338,
      "target2": 3.6384000000000003,
      "riskRewardRatio": "1:2",
      "positionSize": 2955.0342,
      "status": "closed",
      "exitTime": "2024-04-10T19:58:00.000Z",
      "exitPrice": 2.95,
      "exitReason": "end_of_day",
      "pnl": -72.88419999999978,
      "pnlPercent": -2.466441843549553
    },
    {
      "symbol": "TPET",
      "date": "2024-04-10",
      "entryTime": "2024-04-10T14:44:00.000Z",
      "entryPrice": 2.798,
      "stopLoss": 2.412,
      "target1": 3.5700000000000003,
      "target2": 3.9560000000000004,
      "riskRewardRatio": "1:2",
      "positionSize": 1449.364,
      "status": "closed",
      "exitTime": "2024-04-10T18:33:00.000Z",
      "exitPrice": 3.5700000000000003,
      "exitReason": "target1",
      "pnl": 399.89600000000013,
      "pnlPercent": 27.59113652609007
    },
    {
      "symbol": "LPTX",
      "date": "2024-04-11",
      "entryTime": "2024-04-11T14:44:00.000Z",
      "entryPrice": 3.52,
      "stopLoss": 3.025,
      "target1": 4.51,
      "target2": 5.005000000000001,
      "riskRewardRatio": "1:2",
      "positionSize": 1422.08,
      "status": "closed",
      "exitTime": "2024-04-11T20:24:00.000Z",
      "exitPrice": 3.025,
      "exitReason": "stop_loss",
      "pnl": -199.98000000000005,
      "pnlPercent": -14.062500000000004
    },
    {
      "symbol": "BPTH",
      "date": "2024-04-18",
      "entryTime": "2024-04-18T14:44:00.000Z",
      "entryPrice": 6.5503,
      "stopLoss": 3.16,
      "target1": 13.3309,
      "target2": 16.7212,
      "riskRewardRatio": "1:2",
      "positionSize": 379.9174,
      "status": "closed",
      "exitTime": "2024-04-18T20:59:00.000Z",
      "exitPrice": 4.48,
      "exitReason": "end_of_day",
      "pnl": -120.07739999999998,
      "pnlPercent": -31.606185976214825
    },
    {
      "symbol": "SMSI",
      "date": "2024-04-18",
      "entryTime": "2024-04-18T14:46:00.000Z",
      "entryPrice": 2.66,
      "stopLoss": 2.02,
      "target1": 3.9400000000000004,
      "target2": 4.58,
      "riskRewardRatio": "1:2",
      "positionSize": 829.9200000000001,
      "status": "closed",
      "exitTime": "2024-04-18T18:11:00.000Z",
      "exitPrice": 2.02,
      "exitReason": "stop_loss",
      "pnl": -199.68000000000004,
      "pnlPercent": -24.060150375939855
    },
    {
      "symbol": "AGBA",
      "date": "2024-04-30",
      "entryTime": "2024-04-30T14:44:00.000Z",
      "entryPrice": 7.6206,
      "stopLoss": 4.7922,
      "target1": 13.277399999999998,
      "target2": 16.1058,
      "riskRewardRatio": "1:2",
      "positionSize": 533.442,
      "status": "closed",
      "exitTime": "2024-04-30T20:58:00.000Z",
      "exitPrice": 5.7217,
      "exitReason": "end_of_day",
      "pnl": -132.92299999999994,
      "pnlPercent": -24.917985460462425
    },
    {
      "symbol": "SNTI",
      "date": "2024-04-30",
      "entryTime": "2024-04-30T15:05:00.000Z",
      "entryPrice": 4,
      "stopLoss": 3.09,
      "target1": 5.82,
      "target2": 6.73,
      "riskRewardRatio": "1:2",
      "positionSize": 876,
      "status": "closed",
      "exitTime": "2024-04-30T20:58:00.000Z",
      "exitPrice": 3.6,
      "exitReason": "end_of_day",
      "pnl": -87.59999999999998,
      "pnlPercent": -9.999999999999998
    },
    {
      "symbol": "ZKIN",
      "date": "2024-04-30",
      "entryTime": "2024-04-30T15:44:00.000Z",
      "entryPrice": 4.6935,
      "stopLoss": 4.515,
      "target1": 5.050500000000001,
      "target2": 5.229000000000002,
      "riskRewardRatio": "1:2",
      "positionSize": 5256.72,
      "status": "closed",
      "exitTime": "2024-04-30T15:51:00.000Z",
      "exitPrice": 4.515,
      "exitReason": "stop_loss",
      "pnl": -199.9200000000006,
      "pnlPercent": -3.803131991051466
    },
    {
      "symbol": "SELF",
      "date": "2024-05-07",
      "entryTime": "2024-05-07T14:44:00.000Z",
      "entryPrice": 5.2725,
      "stopLoss": 4.36,
      "target1": 7.097499999999999,
      "target2": 8.009999999999998,
      "riskRewardRatio": "1:2",
      "positionSize": 1154.6775,
      "status": "closed",
      "exitTime": "2024-05-07T20:43:00.000Z",
      "exitPrice": 5.34,
      "exitReason": "end_of_day",
      "pnl": 14.782499999999978,
      "pnlPercent": 1.2802275960170677
    },
    {
      "symbol": "SGD",
      "date": "2024-05-08",
      "entryTime": "2024-05-08T14:44:00.000Z",
      "entryPrice": 10.31,
      "stopLoss": 5.222,
      "target1": 20.486,
      "target2": 25.573999999999998,
      "riskRewardRatio": "1:2",
      "positionSize": 402.09000000000003,
      "status": "closed",
      "exitTime": "2024-05-08T20:59:00.000Z",
      "exitPrice": 12.21,
      "exitReason": "end_of_day",
      "pnl": 74.10000000000001,
      "pnlPercent": 18.428709990300682
    },
    {
      "symbol": "BIGC",
      "date": "2024-05-09",
      "entryTime": "2024-05-09T14:44:00.000Z",
      "entryPrice": 7.68,
      "stopLoss": 6.69,
      "target1": 9.659999999999998,
      "target2": 10.649999999999999,
      "riskRewardRatio": "1:2",
      "positionSize": 1551.36,
      "status": "closed",
      "exitTime": "2024-05-09T20:42:00.000Z",
      "exitPrice": 7.6088,
      "exitReason": "end_of_day",
      "pnl": -14.38240000000003,
      "pnlPercent": -0.9270833333333353
    },
    {
      "symbol": "NOVA",
      "date": "2024-05-14",
      "entryTime": "2024-05-14T14:44:00.000Z",
      "entryPrice": 5.165,
      "stopLoss": 4.19,
      "target1": 7.114999999999999,
      "target2": 8.09,
      "riskRewardRatio": "1:2",
      "positionSize": 1058.825,
      "status": "closed",
      "exitTime": "2024-05-14T20:55:00.000Z",
      "exitPrice": 5.47,
      "exitReason": "end_of_day",
      "pnl": 62.52499999999994,
      "pnlPercent": 5.905130687318485
    },
    {
      "symbol": "BSFC",
      "date": "2024-05-15",
      "entryTime": "2024-05-15T14:44:00.000Z",
      "entryPrice": 3.075,
      "stopLoss": 2.745,
      "target1": 3.7350000000000003,
      "target2": 4.065,
      "riskRewardRatio": "1:2",
      "positionSize": 1863.45,
      "status": "closed",
      "exitTime": "2024-05-15T20:39:00.000Z",
      "exitPrice": 3.7350000000000003,
      "exitReason": "target1",
      "pnl": 399.9600000000001,
      "pnlPercent": 21.463414634146343
    },
    {
      "symbol": "EVGN",
      "date": "2024-05-23",
      "entryTime": "2024-05-23T15:05:00.000Z",
      "entryPrice": 8,
      "stopLoss": 7.398,
      "target1": 9.204,
      "target2": 9.806000000000001,
      "riskRewardRatio": "1:2",
      "positionSize": 2656,
      "status": "closed",
      "exitTime": "2024-05-23T19:44:00.000Z",
      "exitPrice": 7.398,
      "exitReason": "stop_loss",
      "pnl": -199.8640000000001,
      "pnlPercent": -7.525000000000004
    },
    {
      "symbol": "RRGB",
      "date": "2024-05-30",
      "entryTime": "2024-05-30T14:44:00.000Z",
      "entryPrice": 7.805,
      "stopLoss": 7.4,
      "target1": 8.614999999999998,
      "target2": 9.019999999999998,
      "riskRewardRatio": "1:2",
      "positionSize": 3847.865,
      "status": "closed",
      "exitTime": "2024-05-30T15:58:00.000Z",
      "exitPrice": 7.4,
      "exitReason": "stop_loss",
      "pnl": -199.66499999999968,
      "pnlPercent": -5.188981422165271
    },
    {
      "symbol": "FRES",
      "date": "2024-06-04",
      "entryTime": "2024-06-04T14:44:00.000Z",
      "entryPrice": 4,
      "stopLoss": 3.705,
      "target1": 4.59,
      "target2": 4.885,
      "riskRewardRatio": "1:2",
      "positionSize": 2708,
      "status": "closed",
      "exitTime": "2024-06-04T17:50:00.000Z",
      "exitPrice": 4.59,
      "exitReason": "target1",
      "pnl": 399.4299999999999,
      "pnlPercent": 14.749999999999996
    },
    {
      "symbol": "MITQ",
      "date": "2024-06-05",
      "entryTime": "2024-06-05T14:44:00.000Z",
      "entryPrice": 1.095,
      "stopLoss": 0.79,
      "target1": 1.7049999999999998,
      "target2": 2.01,
      "riskRewardRatio": "1:2",
      "positionSize": 717.225,
      "status": "closed",
      "exitTime": "2024-06-05T20:59:00.000Z",
      "exitPrice": 1.02,
      "exitReason": "end_of_day",
      "pnl": -49.12499999999997,
      "pnlPercent": -6.849315068493146
    },
    {
      "symbol": "RWOD",
      "date": "2024-06-11",
      "entryTime": "2024-06-11T14:50:00.000Z",
      "entryPrice": 6.8,
      "stopLoss": 5.68,
      "target1": 9.04,
      "target2": 10.16,
      "riskRewardRatio": "1:2",
      "positionSize": 1210.3999999999999,
      "status": "closed",
      "exitTime": "2024-06-11T16:42:00.000Z",
      "exitPrice": 5.68,
      "exitReason": "stop_loss",
      "pnl": -199.36,
      "pnlPercent": -16.47058823529412
    },
    {
      "symbol": "NCI",
      "date": "2024-06-13",
      "entryTime": "2024-06-13T14:44:00.000Z",
      "entryPrice": 3.6915,
      "stopLoss": 3.55,
      "target1": 3.9745000000000004,
      "target2": 4.1160000000000005,
      "riskRewardRatio": "1:2",
      "positionSize": 5216.0895,
      "status": "closed",
      "exitTime": "2024-06-13T15:39:00.000Z",
      "exitPrice": 3.55,
      "exitReason": "stop_loss",
      "pnl": -199.93950000000027,
      "pnlPercent": -3.833130163890022
    },
    {
      "symbol": "SNTI",
      "date": "2024-06-25",
      "entryTime": "2024-06-25T14:44:00.000Z",
      "entryPrice": 3.18,
      "stopLoss": 2.7,
      "target1": 4.140000000000001,
      "target2": 4.62,
      "riskRewardRatio": "1:2",
      "positionSize": 1322.88,
      "status": "closed",
      "exitTime": "2024-06-25T20:59:00.000Z",
      "exitPrice": 2.962,
      "exitReason": "end_of_day",
      "pnl": -90.68799999999999,
      "pnlPercent": -6.855345911949684
    },
    {
      "symbol": "AIEV",
      "date": "2024-06-26",
      "entryTime": "2024-06-26T14:44:00.000Z",
      "entryPrice": 2.4387,
      "stopLoss": 1.58,
      "target1": 4.1560999999999995,
      "target2": 5.014799999999999,
      "riskRewardRatio": "1:2",
      "positionSize": 565.7783999999999,
      "status": "closed",
      "exitTime": "2024-06-26T20:56:00.000Z",
      "exitPrice": 1.94,
      "exitReason": "end_of_day",
      "pnl": -115.69839999999998,
      "pnlPercent": -20.449419772829785
    },
    {
      "symbol": "BSFC",
      "date": "2024-06-27",
      "entryTime": "2024-06-27T14:44:00.000Z",
      "entryPrice": 2.47,
      "stopLoss": 1.78,
      "target1": 3.8500000000000005,
      "target2": 4.540000000000001,
      "riskRewardRatio": "1:2",
      "positionSize": 713.83,
      "status": "closed",
      "exitTime": "2024-06-27T20:59:00.000Z",
      "exitPrice": 2.18,
      "exitReason": "end_of_day",
      "pnl": -83.81000000000002,
      "pnlPercent": -11.74089068825911
    },
    {
      "symbol": "ZAPP",
      "date": "2024-07-02",
      "entryTime": "2024-07-02T14:44:00.000Z",
      "entryPrice": 2.895,
      "stopLoss": 1.86,
      "target1": 4.965,
      "target2": 6,
      "riskRewardRatio": "1:2",
      "positionSize": 558.735,
      "status": "closed",
      "exitTime": "2024-07-02T20:59:00.000Z",
      "exitPrice": 2.38,
      "exitReason": "end_of_day",
      "pnl": -99.39500000000002,
      "pnlPercent": -17.789291882556135
    },
    {
      "symbol": "BEEM",
      "date": "2024-07-02",
      "entryTime": "2024-07-02T14:52:00.000Z",
      "entryPrice": 4.9999,
      "stopLoss": 4.38,
      "target1": 6.239700000000001,
      "target2": 6.859600000000001,
      "riskRewardRatio": "1:2",
      "positionSize": 1609.9678000000001,
      "status": "closed",
      "exitTime": "2024-07-02T20:24:00.000Z",
      "exitPrice": 5.3384,
      "exitReason": "end_of_day",
      "pnl": 108.99699999999993,
      "pnlPercent": 6.77013540270805
    },
    {
      "symbol": "IDR",
      "date": "2024-07-02",
      "entryTime": "2024-07-02T14:58:00.000Z",
      "entryPrice": 10.78,
      "stopLoss": 9.75,
      "target1": 12.839999999999998,
      "target2": 13.869999999999997,
      "riskRewardRatio": "1:2",
      "positionSize": 2091.3199999999997,
      "status": "closed",
      "exitTime": "2024-07-02T19:59:00.000Z",
      "exitPrice": 10.7335,
      "exitReason": "end_of_day",
      "pnl": -9.020999999999997,
      "pnlPercent": -0.4313543599257884
    },
    {
      "symbol": "KOSS",
      "date": "2024-07-03",
      "entryTime": "2024-07-03T14:44:00.000Z",
      "entryPrice": 8.85,
      "stopLoss": 5,
      "target1": 16.549999999999997,
      "target2": 20.4,
      "riskRewardRatio": "1:2",
      "positionSize": 451.34999999999997,
      "status": "closed",
      "exitTime": "2024-07-03T16:13:00.000Z",
      "exitPrice": 16.549999999999997,
      "exitReason": "target1",
      "pnl": 392.6999999999999,
      "pnlPercent": 87.0056497175141
    },
    {
      "symbol": "TKLF",
      "date": "2024-07-18",
      "entryTime": "2024-07-18T14:44:00.000Z",
      "entryPrice": 6.561,
      "stopLoss": 5.6,
      "target1": 8.483,
      "target2": 9.444,
      "riskRewardRatio": "1:2",
      "positionSize": 1364.688,
      "status": "closed",
      "exitTime": "2024-07-18T16:49:00.000Z",
      "exitPrice": 8.483,
      "exitReason": "target1",
      "pnl": 399.7760000000001,
      "pnlPercent": 29.294314891022722
    },
    {
      "symbol": "SSKN",
      "date": "2024-07-18",
      "entryTime": "2024-07-18T15:18:00.000Z",
      "entryPrice": 3.42,
      "stopLoss": 3.26,
      "target1": 3.74,
      "target2": 3.9000000000000004,
      "riskRewardRatio": "1:2",
      "positionSize": 4271.58,
      "status": "closed",
      "exitTime": "2024-07-18T18:33:00.000Z",
      "exitPrice": 3.74,
      "exitReason": "target1",
      "pnl": 399.68000000000035,
      "pnlPercent": 9.356725146198839
    },
    {
      "symbol": "ARTL",
      "date": "2024-07-18",
      "entryTime": "2024-07-18T15:23:00.000Z",
      "entryPrice": 8.04,
      "stopLoss": 7.74,
      "target1": 8.639999999999997,
      "target2": 8.939999999999996,
      "riskRewardRatio": "1:2",
      "positionSize": 5354.639999999999,
      "status": "closed",
      "exitTime": "2024-07-18T18:47:00.000Z",
      "exitPrice": 8.639999999999997,
      "exitReason": "target1",
      "pnl": 399.5999999999986,
      "pnlPercent": 7.462686567164154
    },
    {
      "symbol": "SOAR",
      "date": "2024-07-23",
      "entryTime": "2024-07-23T14:44:00.000Z",
      "entryPrice": 16.855,
      "stopLoss": 13.075,
      "target1": 24.415000000000003,
      "target2": 28.195000000000004,
      "riskRewardRatio": "1:2",
      "positionSize": 876.46,
      "status": "closed",
      "exitTime": "2024-07-23T16:15:00.000Z",
      "exitPrice": 13.075,
      "exitReason": "stop_loss",
      "pnl": -196.56000000000006,
      "pnlPercent": -22.426579649955507
    },
    {
      "symbol": "FEIM",
      "date": "2024-07-23",
      "entryTime": "2024-07-23T14:48:00.000Z",
      "entryPrice": 12.95,
      "stopLoss": 12.55,
      "target1": 13.749999999999996,
      "target2": 14.149999999999995,
      "riskRewardRatio": "1:2",
      "positionSize": 6475,
      "status": "closed",
      "exitTime": "2024-07-23T20:05:00.000Z",
      "exitPrice": 13.749999999999996,
      "exitReason": "target1",
      "pnl": 399.9999999999986,
      "pnlPercent": 6.177606177606156
    },
    {
      "symbol": "BALY",
      "date": "2024-07-25",
      "entryTime": "2024-07-25T14:44:00.000Z",
      "entryPrice": 16.81,
      "stopLoss": 16.16,
      "target1": 18.109999999999996,
      "target2": 18.759999999999994,
      "riskRewardRatio": "1:2",
      "positionSize": 5160.669999999999,
      "status": "closed",
      "exitTime": "2024-07-25T20:53:00.000Z",
      "exitPrice": 16.8702,
      "exitReason": "end_of_day",
      "pnl": 18.481400000000555,
      "pnlPercent": 0.35812016656753015
    },
    {
      "symbol": "BFRG",
      "date": "2024-07-25",
      "entryTime": "2024-07-25T14:44:00.000Z",
      "entryPrice": 3.372,
      "stopLoss": 2.65,
      "target1": 4.816,
      "target2": 5.538,
      "riskRewardRatio": "1:2",
      "positionSize": 934.044,
      "status": "closed",
      "exitTime": "2024-07-25T20:59:00.000Z",
      "exitPrice": 3.18,
      "exitReason": "end_of_day",
      "pnl": -53.183999999999926,
      "pnlPercent": -5.693950177935935
    },
    {
      "symbol": "NVDX",
      "date": "2024-07-31",
      "entryTime": "2024-07-31T14:44:00.000Z",
      "entryPrice": 13.85,
      "stopLoss": 12.5,
      "target1": 16.549999999999997,
      "target2": 17.9,
      "riskRewardRatio": "1:2",
      "positionSize": 2049.7999999999997,
      "status": "closed",
      "exitTime": "2024-07-31T20:58:00.000Z",
      "exitPrice": 14.86,
      "exitReason": "end_of_day",
      "pnl": 149.47999999999996,
      "pnlPercent": 7.292418772563175
    },
    {
      "symbol": "ICLK",
      "date": "2024-08-06",
      "entryTime": "2024-08-06T15:05:00.000Z",
      "entryPrice": 3.0653,
      "stopLoss": 2.4,
      "target1": 4.395900000000001,
      "target2": 5.061200000000001,
      "riskRewardRatio": "1:2",
      "positionSize": 919.59,
      "status": "closed",
      "exitTime": "2024-08-06T19:58:00.000Z",
      "exitPrice": 2.88,
      "exitReason": "end_of_day",
      "pnl": -55.590000000000074,
      "pnlPercent": -6.045085309757617
    },
    {
      "symbol": "TENX",
      "date": "2024-08-13",
      "entryTime": "2024-08-13T15:16:00.000Z",
      "entryPrice": 3.8901,
      "stopLoss": 3.7,
      "target1": 4.270299999999999,
      "target2": 4.460399999999999,
      "riskRewardRatio": "1:2",
      "positionSize": 4092.3851999999997,
      "status": "closed",
      "exitTime": "2024-08-13T20:46:00.000Z",
      "exitPrice": 4.1,
      "exitReason": "end_of_day",
      "pnl": 220.81479999999974,
      "pnlPercent": 5.395748181280681
    },
    {
      "symbol": "NVDX",
      "date": "2024-08-13",
      "entryTime": "2024-08-13T14:44:00.000Z",
      "entryPrice": 13.33,
      "stopLoss": 12.28,
      "target1": 15.430000000000001,
      "target2": 16.480000000000004,
      "riskRewardRatio": "1:2",
      "positionSize": 2532.7,
      "status": "closed",
      "exitTime": "2024-08-13T20:58:00.000Z",
      "exitPrice": 13.7899,
      "exitReason": "end_of_day",
      "pnl": 87.38099999999987,
      "pnlPercent": 3.450112528132028
    },
    {
      "symbol": "AZTR",
      "date": "2024-08-21",
      "entryTime": "2024-08-21T14:44:00.000Z",
      "entryPrice": 4.662,
      "stopLoss": 4.4296,
      "target1": 5.1268,
      "target2": 5.3592,
      "riskRewardRatio": "1:2",
      "positionSize": 4009.3199999999997,
      "status": "closed",
      "exitTime": "2024-08-21T15:48:00.000Z",
      "exitPrice": 4.4296,
      "exitReason": "stop_loss",
      "pnl": -199.86400000000015,
      "pnlPercent": -4.9849849849849885
    },
    {
      "symbol": "AZTR",
      "date": "2024-08-22",
      "entryTime": "2024-08-22T14:48:00.000Z",
      "entryPrice": 4.7832,
      "stopLoss": 4.2624,
      "target1": 5.824799999999999,
      "target2": 6.345599999999998,
      "riskRewardRatio": "1:2",
      "positionSize": 1836.7487999999998,
      "status": "closed",
      "exitTime": "2024-08-22T20:59:00.000Z",
      "exitPrice": 4.8352,
      "exitReason": "end_of_day",
      "pnl": 19.96800000000019,
      "pnlPercent": 1.087138317444399
    },
    {
      "symbol": "ENSC",
      "date": "2024-08-27",
      "entryTime": "2024-08-27T14:44:00.000Z",
      "entryPrice": 9.3255,
      "stopLoss": 6.66,
      "target1": 14.6565,
      "target2": 17.322,
      "riskRewardRatio": "1:2",
      "positionSize": 699.4125,
      "status": "closed",
      "exitTime": "2024-08-27T20:59:00.000Z",
      "exitPrice": 9.3,
      "exitReason": "end_of_day",
      "pnl": -1.9124999999999392,
      "pnlPercent": -0.27344378317515616
    },
    {
      "symbol": "OSS",
      "date": "2024-08-28",
      "entryTime": "2024-08-28T14:46:00.000Z",
      "entryPrice": 2.8812,
      "stopLoss": 2.58,
      "target1": 3.4836000000000005,
      "target2": 3.7848000000000006,
      "riskRewardRatio": "1:2",
      "positionSize": 1913.1168000000002,
      "status": "closed",
      "exitTime": "2024-08-28T20:54:00.000Z",
      "exitPrice": 2.71,
      "exitReason": "end_of_day",
      "pnl": -113.67680000000016,
      "pnlPercent": -5.941968624184375
    },
    {
      "symbol": "JBDI",
      "date": "2024-08-28",
      "entryTime": "2024-08-28T14:44:00.000Z",
      "entryPrice": 12.465,
      "stopLoss": 9.26,
      "target1": 18.875,
      "target2": 22.08,
      "riskRewardRatio": "1:2",
      "positionSize": 772.83,
      "status": "closed",
      "exitTime": "2024-08-28T20:59:00.000Z",
      "exitPrice": 15,
      "exitReason": "end_of_day",
      "pnl": 157.17000000000002,
      "pnlPercent": 20.336943441636585
    },
    {
      "symbol": "TOVX",
      "date": "2024-08-29",
      "entryTime": "2024-08-29T14:44:00.000Z",
      "entryPrice": 3.9,
      "stopLoss": 3.29,
      "target1": 5.119999999999999,
      "target2": 5.7299999999999995,
      "riskRewardRatio": "1:2",
      "positionSize": 1275.3,
      "status": "closed",
      "exitTime": "2024-08-29T20:59:00.000Z",
      "exitPrice": 4.26,
      "exitReason": "end_of_day",
      "pnl": 117.71999999999996,
      "pnlPercent": 9.230769230769226
    },
    {
      "symbol": "TATT",
      "date": "2024-08-29",
      "entryTime": "2024-08-29T15:37:00.000Z",
      "entryPrice": 17.02,
      "stopLoss": 16.5,
      "target1": 18.06,
      "target2": 18.58,
      "riskRewardRatio": "1:2",
      "positionSize": 6535.68,
      "status": "closed",
      "exitTime": "2024-08-29T19:59:00.000Z",
      "exitPrice": 17.9837,
      "exitReason": "end_of_day",
      "pnl": 370.06079999999974,
      "pnlPercent": 5.662162162162159
    },
    {
      "symbol": "CNFR",
      "date": "2024-09-04",
      "entryTime": "2024-09-04T14:44:00.000Z",
      "entryPrice": 1.41,
      "stopLoss": 1.25,
      "target1": 1.7299999999999998,
      "target2": 1.8899999999999997,
      "riskRewardRatio": "1:2",
      "positionSize": 1762.5,
      "status": "closed",
      "exitTime": "2024-09-04T20:59:00.000Z",
      "exitPrice": 1.47,
      "exitReason": "end_of_day",
      "pnl": 75.00000000000007,
      "pnlPercent": 4.255319148936175
    },
    {
      "symbol": "SOAR",
      "date": "2024-09-05",
      "entryTime": "2024-09-05T14:44:00.000Z",
      "entryPrice": 13.04,
      "stopLoss": 10.875,
      "target1": 17.369999999999997,
      "target2": 19.534999999999997,
      "riskRewardRatio": "1:2",
      "positionSize": 1199.6799999999998,
      "status": "closed",
      "exitTime": "2024-09-05T20:58:00.000Z",
      "exitPrice": 11.9975,
      "exitReason": "end_of_day",
      "pnl": -95.90999999999988,
      "pnlPercent": -7.994631901840481
    },
    {
      "symbol": "AEHR",
      "date": "2024-09-05",
      "entryTime": "2024-09-05T14:44:00.000Z",
      "entryPrice": 14.67,
      "stopLoss": 13.36,
      "target1": 17.29,
      "target2": 18.6,
      "riskRewardRatio": "1:2",
      "positionSize": 2229.84,
      "status": "closed",
      "exitTime": "2024-09-05T20:00:00.000Z",
      "exitPrice": 14,
      "exitReason": "end_of_day",
      "pnl": -101.83999999999999,
      "pnlPercent": -4.567143830947511
    },
    {
      "symbol": "ESGL",
      "date": "2024-09-10",
      "entryTime": "2024-09-10T15:06:00.000Z",
      "entryPrice": 1.29,
      "stopLoss": 1.03,
      "target1": 1.81,
      "target2": 2.0700000000000003,
      "riskRewardRatio": "1:2",
      "positionSize": 992.01,
      "status": "closed",
      "exitTime": "2024-09-10T20:17:00.000Z",
      "exitPrice": 1.29,
      "exitReason": "end_of_day",
      "pnl": 0,
      "pnlPercent": 0
    },
    {
      "symbol": "AERT",
      "date": "2024-09-10",
      "entryTime": "2024-09-10T15:15:00.000Z",
      "entryPrice": 2.35,
      "stopLoss": 1.959,
      "target1": 3.132,
      "target2": 3.523,
      "riskRewardRatio": "1:2",
      "positionSize": 1200.8500000000001,
      "status": "closed",
      "exitTime": "2024-09-10T20:59:00.000Z",
      "exitPrice": 2.36,
      "exitReason": "end_of_day",
      "pnl": 5.109999999999891,
      "pnlPercent": 0.4255319148936079
    },
    {
      "symbol": "SLGL",
      "date": "2024-09-10",
      "entryTime": "2024-09-10T17:22:00.000Z",
      "entryPrice": 6.5,
      "stopLoss": 6.1,
      "target1": 7.300000000000001,
      "target2": 7.700000000000001,
      "riskRewardRatio": "1:2",
      "positionSize": 3243.5,
      "status": "closed",
      "exitTime": "2024-09-10T19:56:00.000Z",
      "exitPrice": 6.3705,
      "exitReason": "end_of_day",
      "pnl": -64.62050000000008,
      "pnlPercent": -1.992307692307695
    },
    {
      "symbol": "LAAC",
      "date": "2024-09-11",
      "entryTime": "2024-09-11T14:44:00.000Z",
      "entryPrice": 2.48,
      "stopLoss": 2.21,
      "target1": 3.02,
      "target2": 3.29,
      "riskRewardRatio": "1:2",
      "positionSize": 1835.2,
      "status": "closed",
      "exitTime": "2024-09-11T20:48:00.000Z",
      "exitPrice": 2.4415,
      "exitReason": "end_of_day",
      "pnl": -28.489999999999984,
      "pnlPercent": -1.5524193548387089
    },
    {
      "symbol": "SWVL",
      "date": "2024-09-18",
      "entryTime": "2024-09-18T14:45:00.000Z",
      "entryPrice": 4.32,
      "stopLoss": 3.11,
      "target1": 6.740000000000001,
      "target2": 7.950000000000001,
      "riskRewardRatio": "1:2",
      "positionSize": 712.8000000000001,
      "status": "closed",
      "exitTime": "2024-09-18T17:53:00.000Z",
      "exitPrice": 3.11,
      "exitReason": "stop_loss",
      "pnl": -199.65000000000006,
      "pnlPercent": -28.009259259259267
    },
    {
      "symbol": "VVOS",
      "date": "2024-09-18",
      "entryTime": "2024-09-18T14:44:00.000Z",
      "entryPrice": 3.552,
      "stopLoss": 3,
      "target1": 4.656000000000001,
      "target2": 5.208,
      "riskRewardRatio": "1:2",
      "positionSize": 1285.824,
      "status": "closed",
      "exitTime": "2024-09-18T16:11:00.000Z",
      "exitPrice": 4.656000000000001,
      "exitReason": "target1",
      "pnl": 399.6480000000002,
      "pnlPercent": 31.081081081081095
    },
    {
      "symbol": "CNEY",
      "date": "2024-09-26",
      "entryTime": "2024-09-26T14:44:00.000Z",
      "entryPrice": 19.5,
      "stopLoss": 10.5275,
      "target1": 37.445,
      "target2": 46.417500000000004,
      "riskRewardRatio": "1:2",
      "positionSize": 429,
      "status": "closed",
      "exitTime": "2024-09-26T20:59:00.000Z",
      "exitPrice": 16.4875,
      "exitReason": "end_of_day",
      "pnl": -66.27499999999998,
      "pnlPercent": -15.448717948717944
    },
    {
      "symbol": "UAVS",
      "date": "2024-10-01",
      "entryTime": "2024-10-01T14:44:00.000Z",
      "entryPrice": 7.965,
      "stopLoss": 6.255,
      "target1": 11.385,
      "target2": 13.094999999999999,
      "riskRewardRatio": "1:2",
      "positionSize": 923.9399999999999,
      "status": "closed",
      "exitTime": "2024-10-01T20:59:00.000Z",
      "exitPrice": 7.105,
      "exitReason": "end_of_day",
      "pnl": -99.75999999999993,
      "pnlPercent": -10.797237915881977
    },
    {
      "symbol": "TOP",
      "date": "2024-10-02",
      "entryTime": "2024-10-02T14:44:00.000Z",
      "entryPrice": 2.1499,
      "stopLoss": 1.92,
      "target1": 2.6097000000000006,
      "target2": 2.839600000000001,
      "riskRewardRatio": "1:2",
      "positionSize": 1868.2631000000001,
      "status": "closed",
      "exitTime": "2024-10-02T15:27:00.000Z",
      "exitPrice": 2.6097000000000006,
      "exitReason": "target1",
      "pnl": 399.5662000000004,
      "pnlPercent": 21.387041257732935
    },
    {
      "symbol": "WW",
      "date": "2024-10-09",
      "entryTime": "2024-10-09T14:44:00.000Z",
      "entryPrice": 1.425,
      "stopLoss": 1.28,
      "target1": 1.715,
      "target2": 1.86,
      "riskRewardRatio": "1:2",
      "positionSize": 1965.075,
      "status": "closed",
      "exitTime": "2024-10-09T15:58:00.000Z",
      "exitPrice": 1.715,
      "exitReason": "target1",
      "pnl": 399.91,
      "pnlPercent": 20.35087719298246
    },
    {
      "symbol": "XWEL",
      "date": "2024-10-09",
      "entryTime": "2024-10-09T16:29:00.000Z",
      "entryPrice": 1.81,
      "stopLoss": 1.6,
      "target1": 2.23,
      "target2": 2.44,
      "riskRewardRatio": "1:2",
      "positionSize": 1723.1200000000001,
      "status": "closed",
      "exitTime": "2024-10-09T18:55:00.000Z",
      "exitPrice": 1.7818,
      "exitReason": "end_of_day",
      "pnl": -26.846400000000003,
      "pnlPercent": -1.558011049723757
    },
    {
      "symbol": "ATOM",
      "date": "2024-10-10",
      "entryTime": "2024-10-10T14:52:00.000Z",
      "entryPrice": 3.5,
      "stopLoss": 3.16,
      "target1": 4.18,
      "target2": 4.52,
      "riskRewardRatio": "1:2",
      "positionSize": 2058,
      "status": "closed",
      "exitTime": "2024-10-10T20:25:00.000Z",
      "exitPrice": 3.69,
      "exitReason": "end_of_day",
      "pnl": 111.71999999999997,
      "pnlPercent": 5.428571428571427
    },
    {
      "symbol": "WBA",
      "date": "2024-10-15",
      "entryTime": "2024-10-15T14:44:00.000Z",
      "entryPrice": 10.2549,
      "stopLoss": 8.7,
      "target1": 13.3647,
      "target2": 14.919599999999999,
      "riskRewardRatio": "1:2",
      "positionSize": 1312.6272,
      "status": "closed",
      "exitTime": "2024-10-15T20:58:00.000Z",
      "exitPrice": 10.4,
      "exitReason": "end_of_day",
      "pnl": 18.572800000000143,
      "pnlPercent": 1.414933348935642
    },
    {
      "symbol": "BREA",
      "date": "2024-10-17",
      "entryTime": "2024-10-17T14:44:00.000Z",
      "entryPrice": 1.225,
      "stopLoss": 1.08,
      "target1": 1.5150000000000001,
      "target2": 1.6600000000000001,
      "riskRewardRatio": "1:2",
      "positionSize": 1689.275,
      "status": "closed",
      "exitTime": "2024-10-17T14:57:00.000Z",
      "exitPrice": 1.08,
      "exitReason": "stop_loss",
      "pnl": -199.955,
      "pnlPercent": -11.83673469387755
    },
    {
      "symbol": "ZONE",
      "date": "2024-10-17",
      "entryTime": "2024-10-17T19:33:00.000Z",
      "entryPrice": 1.5,
      "stopLoss": 1.34,
      "target1": 1.8199999999999998,
      "target2": 1.9799999999999998,
      "riskRewardRatio": "1:2",
      "positionSize": 1875,
      "status": "closed",
      "exitTime": "2024-10-17T19:40:00.000Z",
      "exitPrice": 1.34,
      "exitReason": "stop_loss",
      "pnl": -199.9999999999999,
      "pnlPercent": -10.666666666666663
    },
    {
      "symbol": "NXL",
      "date": "2024-10-17",
      "entryTime": "2024-10-17T14:44:00.000Z",
      "entryPrice": 1.1974,
      "stopLoss": 1.04,
      "target1": 1.5122,
      "target2": 1.6696,
      "riskRewardRatio": "1:2",
      "positionSize": 1520.698,
      "status": "closed",
      "exitTime": "2024-10-17T20:43:00.000Z",
      "exitPrice": 1.3,
      "exitReason": "end_of_day",
      "pnl": 130.30200000000002,
      "pnlPercent": 8.568565224653419
    },
    {
      "symbol": "PHUN",
      "date": "2024-10-17",
      "entryTime": "2024-10-17T14:44:00.000Z",
      "entryPrice": 7.0301,
      "stopLoss": 6.13,
      "target1": 8.830300000000001,
      "target2": 9.7304,
      "riskRewardRatio": "1:2",
      "positionSize": 1560.6822,
      "status": "closed",
      "exitTime": "2024-10-17T20:59:00.000Z",
      "exitPrice": 7.28,
      "exitReason": "end_of_day",
      "pnl": 55.47780000000005,
      "pnlPercent": 3.5547147266752996
    },
    {
      "symbol": "NITO",
      "date": "2024-10-22",
      "entryTime": "2024-10-22T14:44:00.000Z",
      "entryPrice": 9.485,
      "stopLoss": 8.8585,
      "target1": 10.738,
      "target2": 11.3645,
      "riskRewardRatio": "1:2",
      "positionSize": 3025.7149999999997,
      "status": "closed",
      "exitTime": "2024-10-22T20:59:00.000Z",
      "exitPrice": 9.8,
      "exitReason": "end_of_day",
      "pnl": 100.48500000000041,
      "pnlPercent": 3.3210332103321174
    },
    {
      "symbol": "VRAX",
      "date": "2024-10-22",
      "entryTime": "2024-10-22T15:06:00.000Z",
      "entryPrice": 1.8326,
      "stopLoss": 1.65,
      "target1": 2.1978,
      "target2": 2.3804000000000003,
      "riskRewardRatio": "1:2",
      "positionSize": 2006.6970000000001,
      "status": "closed",
      "exitTime": "2024-10-22T20:43:00.000Z",
      "exitPrice": 1.67,
      "exitReason": "end_of_day",
      "pnl": -178.04700000000008,
      "pnlPercent": -8.872639965076944
    },
    {
      "symbol": "TSLT",
      "date": "2024-10-24",
      "entryTime": "2024-10-24T14:44:00.000Z",
      "entryPrice": 16.5695,
      "stopLoss": 14.79,
      "target1": 20.128500000000006,
      "target2": 21.90800000000001,
      "riskRewardRatio": "1:2",
      "positionSize": 1855.784,
      "status": "closed",
      "exitTime": "2024-10-24T20:59:00.000Z",
      "exitPrice": 17.45,
      "exitReason": "end_of_day",
      "pnl": 98.61599999999976,
      "pnlPercent": 5.313980506352019
    },
    {
      "symbol": "WAVE",
      "date": "2024-10-28",
      "entryTime": "2024-10-28T15:00:00.000Z",
      "entryPrice": 10.32,
      "stopLoss": 9.0007,
      "target1": 12.9586,
      "target2": 14.2779,
      "riskRewardRatio": "1:2",
      "positionSize": 1558.32,
      "status": "closed",
      "exitTime": "2024-10-28T20:55:00.000Z",
      "exitPrice": 10.59,
      "exitReason": "end_of_day",
      "pnl": 40.76999999999994,
      "pnlPercent": 2.6162790697674376
    },
    {
      "symbol": "TZOO",
      "date": "2024-10-28",
      "entryTime": "2024-10-28T14:45:00.000Z",
      "entryPrice": 17.325,
      "stopLoss": 15.69,
      "target1": 20.595,
      "target2": 22.229999999999997,
      "riskRewardRatio": "1:2",
      "positionSize": 2113.65,
      "status": "closed",
      "exitTime": "2024-10-28T19:59:00.000Z",
      "exitPrice": 17.4,
      "exitReason": "end_of_day",
      "pnl": 9.149999999999913,
      "pnlPercent": 0.43290043290042884
    },
    {
      "symbol": "LIXT",
      "date": "2024-10-29",
      "entryTime": "2024-10-29T14:44:00.000Z",
      "entryPrice": 1.91,
      "stopLoss": 1.75,
      "target1": 2.2299999999999995,
      "target2": 2.3899999999999997,
      "riskRewardRatio": "1:2",
      "positionSize": 2387.5,
      "status": "closed",
      "exitTime": "2024-10-29T14:47:00.000Z",
      "exitPrice": 2.2299999999999995,
      "exitReason": "target1",
      "pnl": 399.99999999999955,
      "pnlPercent": 16.753926701570663
    },
    {
      "symbol": "NXL",
      "date": "2024-10-29",
      "entryTime": "2024-10-29T14:44:00.000Z",
      "entryPrice": 2.5906,
      "stopLoss": 2.11,
      "target1": 3.5517999999999996,
      "target2": 4.032399999999999,
      "riskRewardRatio": "1:2",
      "positionSize": 1077.6896,
      "status": "closed",
      "exitTime": "2024-10-29T20:57:00.000Z",
      "exitPrice": 2.61,
      "exitReason": "end_of_day",
      "pnl": 8.070400000000035,
      "pnlPercent": 0.7488612676600048
    },
    {
      "symbol": "MIRA",
      "date": "2024-10-29",
      "entryTime": "2024-10-29T14:44:00.000Z",
      "entryPrice": 1.73,
      "stopLoss": 1.37,
      "target1": 2.4499999999999997,
      "target2": 2.8099999999999996,
      "riskRewardRatio": "1:2",
      "positionSize": 960.15,
      "status": "closed",
      "exitTime": "2024-10-29T20:51:00.000Z",
      "exitPrice": 1.71,
      "exitReason": "end_of_day",
      "pnl": -11.10000000000001,
      "pnlPercent": -1.1560693641618507
    },
    {
      "symbol": "CCEL",
      "date": "2024-10-30",
      "entryTime": "2024-10-30T14:48:00.000Z",
      "entryPrice": 7.99,
      "stopLoss": 5.88,
      "target1": 12.21,
      "target2": 14.32,
      "riskRewardRatio": "1:2",
      "positionSize": 751.0600000000001,
      "status": "closed",
      "exitTime": "2024-10-30T20:33:00.000Z",
      "exitPrice": 7.2,
      "exitReason": "end_of_day",
      "pnl": -74.26,
      "pnlPercent": -9.88735919899875
    },
    {
      "symbol": "AMIX",
      "date": "2024-10-31",
      "entryTime": "2024-10-31T14:44:00.000Z",
      "entryPrice": 12.3,
      "stopLoss": 10.26,
      "target1": 16.380000000000003,
      "target2": 18.42,
      "riskRewardRatio": "1:2",
      "positionSize": 1205.4,
      "status": "closed",
      "exitTime": "2024-10-31T20:59:00.000Z",
      "exitPrice": 14.3,
      "exitReason": "end_of_day",
      "pnl": 196,
      "pnlPercent": 16.260162601626014
    },
    {
      "symbol": "DNB",
      "date": "2024-10-31",
      "entryTime": "2024-10-31T14:44:00.000Z",
      "entryPrice": 12.32,
      "stopLoss": 11.08,
      "target1": 14.8,
      "target2": 16.04,
      "riskRewardRatio": "1:2",
      "positionSize": 1983.52,
      "status": "closed",
      "exitTime": "2024-10-31T20:39:00.000Z",
      "exitPrice": 11.61,
      "exitReason": "end_of_day",
      "pnl": -114.31000000000014,
      "pnlPercent": -5.76298701298702
    },
    {
      "symbol": "ATHA",
      "date": "2024-11-01",
      "entryTime": "2024-11-01T14:44:00.000Z",
      "entryPrice": 5.599,
      "stopLoss": 5.035,
      "target1": 6.727,
      "target2": 7.291,
      "riskRewardRatio": "1:2",
      "positionSize": 1982.046,
      "status": "closed",
      "exitTime": "2024-11-01T16:28:00.000Z",
      "exitPrice": 6.727,
      "exitReason": "target1",
      "pnl": 399.312,
      "pnlPercent": 20.146454724057868
    },
    {
      "symbol": "VMEO",
      "date": "2024-11-05",
      "entryTime": "2024-11-05T14:44:00.000Z",
      "entryPrice": 6.2202,
      "stopLoss": 5.46,
      "target1": 7.740600000000001,
      "target2": 8.500800000000002,
      "riskRewardRatio": "1:2",
      "positionSize": 1635.9126,
      "status": "closed",
      "exitTime": "2024-11-05T20:59:00.000Z",
      "exitPrice": 6.94,
      "exitReason": "end_of_day",
      "pnl": 189.30740000000006,
      "pnlPercent": 11.571975177647024
    },
    {
      "symbol": "NMHI",
      "date": "2024-11-07",
      "entryTime": "2024-11-07T14:44:00.000Z",
      "entryPrice": 4.023,
      "stopLoss": 2.664,
      "target1": 6.740999999999999,
      "target2": 8.099999999999998,
      "riskRewardRatio": "1:2",
      "positionSize": 591.381,
      "status": "closed",
      "exitTime": "2024-11-07T14:49:00.000Z",
      "exitPrice": 6.740999999999999,
      "exitReason": "target1",
      "pnl": 399.5459999999999,
      "pnlPercent": 67.56152125279641
    },
    {
      "symbol": "SHIM",
      "date": "2024-11-12",
      "entryTime": "2024-11-12T14:52:00.000Z",
      "entryPrice": 2.54,
      "stopLoss": 2.28,
      "target1": 3.0600000000000005,
      "target2": 3.3200000000000007,
      "riskRewardRatio": "1:2",
      "positionSize": 1953.26,
      "status": "closed",
      "exitTime": "2024-11-12T15:12:00.000Z",
      "exitPrice": 2.28,
      "exitReason": "stop_loss",
      "pnl": -199.94000000000017,
      "pnlPercent": -10.236220472440955
    },
    {
      "symbol": "ZONE",
      "date": "2024-11-13",
      "entryTime": "2024-11-13T14:45:00.000Z",
      "entryPrice": 2.175,
      "stopLoss": 1.9,
      "target1": 2.7249999999999996,
      "target2": 2.9999999999999996,
      "riskRewardRatio": "1:2",
      "positionSize": 1581.225,
      "status": "closed",
      "exitTime": "2024-11-13T15:33:00.000Z",
      "exitPrice": 1.9,
      "exitReason": "stop_loss",
      "pnl": -199.92499999999993,
      "pnlPercent": -12.643678160919535
    },
    {
      "symbol": "GXAI",
      "date": "2024-11-14",
      "entryTime": "2024-11-14T14:44:00.000Z",
      "entryPrice": 2.1,
      "stopLoss": 1.5,
      "target1": 3.3000000000000003,
      "target2": 3.9000000000000004,
      "riskRewardRatio": "1:2",
      "positionSize": 699.3000000000001,
      "status": "closed",
      "exitTime": "2024-11-14T20:59:00.000Z",
      "exitPrice": 1.745,
      "exitReason": "end_of_day",
      "pnl": -118.21499999999999,
      "pnlPercent": -16.9047619047619
    },
    {
      "symbol": "BENF",
      "date": "2024-11-15",
      "entryTime": "2024-11-15T14:44:00.000Z",
      "entryPrice": 16.56,
      "stopLoss": 10.8,
      "target1": 28.079999999999995,
      "target2": 33.83999999999999,
      "riskRewardRatio": "1:2",
      "positionSize": 563.04,
      "status": "closed",
      "exitTime": "2024-11-15T16:09:00.000Z",
      "exitPrice": 10.8,
      "exitReason": "stop_loss",
      "pnl": -195.83999999999992,
      "pnlPercent": -34.782608695652165
    },
    {
      "symbol": "DEVS",
      "date": "2024-11-22",
      "entryTime": "2024-11-22T14:45:00.000Z",
      "entryPrice": 6.395,
      "stopLoss": 5.023,
      "target1": 9.139,
      "target2": 10.511,
      "riskRewardRatio": "1:2",
      "positionSize": 927.275,
      "status": "closed",
      "exitTime": "2024-11-22T15:01:00.000Z",
      "exitPrice": 9.139,
      "exitReason": "target1",
      "pnl": 397.88,
      "pnlPercent": 42.90852228303362
    },
    {
      "symbol": "IDAI",
      "date": "2024-11-26",
      "entryTime": "2024-11-26T14:44:00.000Z",
      "entryPrice": 6.195,
      "stopLoss": 3.3735,
      "target1": 11.838000000000001,
      "target2": 14.659500000000001,
      "riskRewardRatio": "1:2",
      "positionSize": 433.65000000000003,
      "status": "closed",
      "exitTime": "2024-11-26T20:59:00.000Z",
      "exitPrice": 5.46,
      "exitReason": "end_of_day",
      "pnl": -51.450000000000024,
      "pnlPercent": -11.86440677966102
    },
    {
      "symbol": "SOAR",
      "date": "2024-11-26",
      "entryTime": "2024-11-26T14:44:00.000Z",
      "entryPrice": 8.05,
      "stopLoss": 7.075,
      "target1": 10.000000000000002,
      "target2": 10.975000000000001,
      "riskRewardRatio": "1:2",
      "positionSize": 1650.2500000000002,
      "status": "closed",
      "exitTime": "2024-11-26T20:59:00.000Z",
      "exitPrice": 7.335,
      "exitReason": "end_of_day",
      "pnl": -146.57500000000016,
      "pnlPercent": -8.88198757763976
    },
    {
      "symbol": "IMCC",
      "date": "2024-11-27",
      "entryTime": "2024-11-27T14:44:00.000Z",
      "entryPrice": 3.32,
      "stopLoss": 2.51,
      "target1": 4.9399999999999995,
      "target2": 5.75,
      "riskRewardRatio": "1:2",
      "positionSize": 816.7199999999999,
      "status": "closed",
      "exitTime": "2024-11-27T20:59:00.000Z",
      "exitPrice": 3.68,
      "exitReason": "end_of_day",
      "pnl": 88.56000000000007,
      "pnlPercent": 10.843373493975914
    },
    {
      "symbol": "MDAI",
      "date": "2024-11-27",
      "entryTime": "2024-11-27T14:44:00.000Z",
      "entryPrice": 1.6285,
      "stopLoss": 1.51,
      "target1": 1.8655000000000002,
      "target2": 1.9840000000000002,
      "riskRewardRatio": "1:2",
      "positionSize": 2747.2795,
      "status": "closed",
      "exitTime": "2024-11-27T14:57:00.000Z",
      "exitPrice": 1.51,
      "exitReason": "stop_loss",
      "pnl": -199.9095000000001,
      "pnlPercent": -7.2766349401289565
    },
    {
      "symbol": "EHGO",
      "date": "2024-12-02",
      "entryTime": "2024-12-02T14:44:00.000Z",
      "entryPrice": 4.7,
      "stopLoss": 4.19,
      "target1": 5.72,
      "target2": 6.2299999999999995,
      "riskRewardRatio": "1:2",
      "positionSize": 1842.4,
      "status": "closed",
      "exitTime": "2024-12-02T14:52:00.000Z",
      "exitPrice": 4.19,
      "exitReason": "stop_loss",
      "pnl": -199.9199999999999,
      "pnlPercent": -10.851063829787229
    },
    {
      "symbol": "AISP",
      "date": "2024-12-02",
      "entryTime": "2024-12-02T14:44:00.000Z",
      "entryPrice": 3.7,
      "stopLoss": 3.23,
      "target1": 4.640000000000001,
      "target2": 5.110000000000001,
      "riskRewardRatio": "1:2",
      "positionSize": 1572.5,
      "status": "closed",
      "exitTime": "2024-12-02T17:31:00.000Z",
      "exitPrice": 3.23,
      "exitReason": "stop_loss",
      "pnl": -199.75000000000009,
      "pnlPercent": -12.702702702702705
    },
    {
      "symbol": "RRGB",
      "date": "2024-12-03",
      "entryTime": "2024-12-03T14:44:00.000Z",
      "entryPrice": 6.36,
      "stopLoss": 5.31,
      "target1": 8.46,
      "target2": 9.510000000000002,
      "riskRewardRatio": "1:2",
      "positionSize": 1208.4,
      "status": "closed",
      "exitTime": "2024-12-03T20:59:00.000Z",
      "exitPrice": 5.53,
      "exitReason": "end_of_day",
      "pnl": -157.70000000000002,
      "pnlPercent": -13.050314465408805
    },
    {
      "symbol": "MIGI",
      "date": "2024-12-05",
      "entryTime": "2024-12-05T14:48:00.000Z",
      "entryPrice": 26.564,
      "stopLoss": 15.4,
      "target1": 48.891999999999996,
      "target2": 60.056,
      "riskRewardRatio": "1:2",
      "positionSize": 451.588,
      "status": "closed",
      "exitTime": "2024-12-05T20:59:00.000Z",
      "exitPrice": 26.5,
      "exitReason": "end_of_day",
      "pnl": -1.088000000000001,
      "pnlPercent": -0.24092757114892357
    },
    {
      "symbol": "ZONE",
      "date": "2024-12-11",
      "entryTime": "2024-12-11T14:44:00.000Z",
      "entryPrice": 1.81,
      "stopLoss": 1.53,
      "target1": 2.37,
      "target2": 2.6500000000000004,
      "riskRewardRatio": "1:2",
      "positionSize": 1292.3400000000001,
      "status": "closed",
      "exitTime": "2024-12-11T18:11:00.000Z",
      "exitPrice": 1.53,
      "exitReason": "stop_loss",
      "pnl": -199.92000000000002,
      "pnlPercent": -15.46961325966851
    },
    {
      "symbol": "NXGL",
      "date": "2024-12-12",
      "entryTime": "2024-12-12T14:44:00.000Z",
      "entryPrice": 4.65,
      "stopLoss": 4,
      "target1": 5.950000000000001,
      "target2": 6.600000000000001,
      "riskRewardRatio": "1:2",
      "positionSize": 1427.5500000000002,
      "status": "closed",
      "exitTime": "2024-12-12T20:59:00.000Z",
      "exitPrice": 4.49,
      "exitReason": "end_of_day",
      "pnl": -49.12000000000005,
      "pnlPercent": -3.440860215053766
    },
    {
      "symbol": "LOOP",
      "date": "2024-12-13",
      "entryTime": "2024-12-13T14:44:00.000Z",
      "entryPrice": 1.7301,
      "stopLoss": 1.36,
      "target1": 2.4703,
      "target2": 2.8404,
      "riskRewardRatio": "1:2",
      "positionSize": 934.254,
      "status": "closed",
      "exitTime": "2024-12-13T20:59:00.000Z",
      "exitPrice": 1.8004,
      "exitReason": "end_of_day",
      "pnl": 37.96200000000002,
      "pnlPercent": 4.0633489393676685
    },
    {
      "symbol": "YCBD",
      "date": "2024-12-17",
      "entryTime": "2024-12-17T14:46:00.000Z",
      "entryPrice": 3.1596,
      "stopLoss": 2.4176,
      "target1": 4.6436,
      "target2": 5.3856,
      "riskRewardRatio": "1:2",
      "positionSize": 849.9324,
      "status": "closed",
      "exitTime": "2024-12-17T20:59:00.000Z",
      "exitPrice": 3.512,
      "exitReason": "end_of_day",
      "pnl": 94.79559999999995,
      "pnlPercent": 11.153310545638682
    },
    {
      "symbol": "VRAR",
      "date": "2024-12-18",
      "entryTime": "2024-12-18T14:44:00.000Z",
      "entryPrice": 2.1201,
      "stopLoss": 1.67,
      "target1": 3.0202999999999998,
      "target2": 3.4703999999999997,
      "riskRewardRatio": "1:2",
      "positionSize": 941.3244,
      "status": "closed",
      "exitTime": "2024-12-18T15:56:00.000Z",
      "exitPrice": 3.0202999999999998,
      "exitReason": "target1",
      "pnl": 399.68879999999996,
      "pnlPercent": 42.46026130842884
    },
    {
      "symbol": "SOBR",
      "date": "2024-12-19",
      "entryTime": "2024-12-19T14:44:00.000Z",
      "entryPrice": 10.65,
      "stopLoss": 8,
      "target1": 15.950000000000001,
      "target2": 18.6,
      "riskRewardRatio": "1:2",
      "positionSize": 798.75,
      "status": "closed",
      "exitTime": "2024-12-19T17:50:00.000Z",
      "exitPrice": 15.950000000000001,
      "exitReason": "target1",
      "pnl": 397.50000000000006,
      "pnlPercent": 49.76525821596245
    },
    {
      "symbol": "AZTR",
      "date": "2024-12-19",
      "entryTime": "2024-12-19T15:12:00.000Z",
      "entryPrice": 2.7366,
      "stopLoss": 2.5614,
      "target1": 3.0870000000000006,
      "target2": 3.262200000000001,
      "riskRewardRatio": "1:2",
      "positionSize": 3122.4606000000003,
      "status": "closed",
      "exitTime": "2024-12-19T20:59:00.000Z",
      "exitPrice": 2.664,
      "exitReason": "end_of_day",
      "pnl": -82.8366,
      "pnlPercent": -2.652926989695242
    },
    {
      "symbol": "GXAI",
      "date": "2024-12-23",
      "entryTime": "2024-12-23T14:44:00.000Z",
      "entryPrice": 2.65,
      "stopLoss": 2.38,
      "target1": 3.19,
      "target2": 3.46,
      "riskRewardRatio": "1:2",
      "positionSize": 1961,
      "status": "closed",
      "exitTime": "2024-12-23T17:26:00.000Z",
      "exitPrice": 2.38,
      "exitReason": "stop_loss",
      "pnl": -199.8,
      "pnlPercent": -10.18867924528302
    },
    {
      "symbol": "PDYNW",
      "date": "2024-12-27",
      "entryTime": "2024-12-27T14:44:00.000Z",
      "entryPrice": 1.6,
      "stopLoss": 0.8,
      "target1": 3.2,
      "target2": 4,
      "riskRewardRatio": "1:2",
      "positionSize": 400,
      "status": "closed",
      "exitTime": "2024-12-27T15:12:00.000Z",
      "exitPrice": 0.8,
      "exitReason": "stop_loss",
      "pnl": -200,
      "pnlPercent": -50
    },
    {
      "symbol": "AMBO",
      "date": "2024-12-27",
      "entryTime": "2024-12-27T14:56:00.000Z",
      "entryPrice": 3.48,
      "stopLoss": 2.57,
      "target1": 5.300000000000001,
      "target2": 6.210000000000001,
      "riskRewardRatio": "1:2",
      "positionSize": 762.12,
      "status": "closed",
      "exitTime": "2024-12-27T20:59:00.000Z",
      "exitPrice": 3.09,
      "exitReason": "end_of_day",
      "pnl": -85.41000000000003,
      "pnlPercent": -11.20689655172414
    },
    {
      "symbol": "CCTG",
      "date": "2024-12-30",
      "entryTime": "2024-12-30T14:45:00.000Z",
      "entryPrice": 2.03,
      "stopLoss": 1.81,
      "target1": 2.4699999999999993,
      "target2": 2.689999999999999,
      "riskRewardRatio": "1:2",
      "positionSize": 1845.2699999999998,
      "status": "closed",
      "exitTime": "2024-12-30T20:59:00.000Z",
      "exitPrice": 1.93,
      "exitReason": "end_of_day",
      "pnl": -90.89999999999988,
      "pnlPercent": -4.92610837438423
    },
    {
      "symbol": "UNL",
      "date": "2024-12-30",
      "entryTime": "2024-12-30T14:45:00.000Z",
      "entryPrice": 8.51,
      "stopLoss": 8.1,
      "target1": 9.33,
      "target2": 9.74,
      "riskRewardRatio": "1:2",
      "positionSize": 4144.37,
      "status": "closed",
      "exitTime": "2024-12-30T20:59:00.000Z",
      "exitPrice": 8.28,
      "exitReason": "end_of_day",
      "pnl": -112.0100000000002,
      "pnlPercent": -2.7027027027027075
    },
    {
      "symbol": "BQ",
      "date": "2024-12-30",
      "entryTime": "2024-12-30T15:28:00.000Z",
      "entryPrice": 3.748,
      "stopLoss": 3.298,
      "target1": 4.648000000000001,
      "target2": 5.098000000000001,
      "riskRewardRatio": "1:2",
      "positionSize": 1664.112,
      "status": "closed",
      "exitTime": "2024-12-30T20:54:00.000Z",
      "exitPrice": 3.812,
      "exitReason": "end_of_day",
      "pnl": 28.415999999999826,
      "pnlPercent": 1.7075773745997762
    },
    {
      "symbol": "BTCT",
      "date": "2024-12-31",
      "entryTime": "2024-12-31T14:44:00.000Z",
      "entryPrice": 5.17,
      "stopLoss": 4.53,
      "target1": 6.449999999999999,
      "target2": 7.089999999999999,
      "riskRewardRatio": "1:2",
      "positionSize": 1613.04,
      "status": "closed",
      "exitTime": "2024-12-31T20:59:00.000Z",
      "exitPrice": 4.78,
      "exitReason": "end_of_day",
      "pnl": -121.6799999999999,
      "pnlPercent": -7.54352030947775
    },
    {
      "symbol": "KORE",
      "date": "2024-12-31",
      "entryTime": "2024-12-31T14:44:00.000Z",
      "entryPrice": 2.9806,
      "stopLoss": 2.53,
      "target1": 3.8818,
      "target2": 4.3324,
      "riskRewardRatio": "1:2",
      "positionSize": 1320.4058,
      "status": "closed",
      "exitTime": "2024-12-31T20:59:00.000Z",
      "exitPrice": 3.2,
      "exitReason": "end_of_day",
      "pnl": 97.19420000000011,
      "pnlPercent": 7.360934040126158
    }
  ],
  "summary": {
    "totalTrades": 158,
    "winningTrades": 67,
    "losingTrades": 89,
    "winRate": 42.405063291139236,
    "totalPnL": 890.0062999999984,
    "avgWin": 171.63489104477603,
    "avgLoss": 119.20821797752816,
    "profitFactor": 1.0838874278650974,
    "maxDrawdown": 2427.521599999998,
    "bestTrade": 399.99999999999955,
    "worstTrade": -200
  },
  "monthlyPerformance": [
    {
      "month": "2024-01",
      "trades": 9,
      "pnl": -280.8692999999999,
      "winRate": 33.33333333333333
    },
    {
      "month": "2024-02",
      "trades": 13,
      "pnl": -694.7257999999991,
      "winRate": 38.46153846153847
    },
    {
      "month": "2024-03",
      "trades": 24,
      "pnl": -360.6580999999991,
      "winRate": 37.5
    },
    {
      "month": "2024-04",
      "trades": 14,
      "pnl": -790.1386000000001,
      "winRate": 28.57142857142857
    },
    {
      "month": "2024-05",
      "trades": 7,
      "pnl": 137.45610000000022,
      "winRate": 57.14285714285714
    },
    {
      "month": "2024-06",
      "trades": 7,
      "pnl": -339.1909000000003,
      "winRate": 14.285714285714285
    },
    {
      "month": "2024-07",
      "trades": 12,
      "pnl": 1910.554399999998,
      "winRate": 66.66666666666666
    },
    {
      "month": "2024-08",
      "trades": 10,
      "pnl": 602.0712999999992,
      "winRate": 60
    },
    {
      "month": "2024-09",
      "trades": 10,
      "pnl": -77.0274999999998,
      "winRate": 30
    },
    {
      "month": "2024-10",
      "trades": 21,
      "pnl": 1064.3618000000001,
      "winRate": 61.904761904761905
    },
    {
      "month": "2024-11",
      "trades": 12,
      "pnl": 362.75089999999966,
      "winRate": 41.66666666666667
    },
    {
      "month": "2024-12",
      "trades": 19,
      "pnl": -644.5780000000002,
      "winRate": 31.57894736842105
    }
  ]
}