[
  {
    "symbol": "UNH",
    "timeframe": "1m",
    "open": 324.72,
    "high": 324.72,
    "low": 324.72,
    "close": 324.72,
    "volume": 270,
    "start": "2025-12-24T09:00:00.000Z",
    "end": "2025-12-24T09:01:00.000Z"
  },
  {
    "symbol": "UNH",
    "timeframe": "1m",
    "open": 324.5,
    "high": 324.5,
    "low": 324.5,
    "close": 324.5,
    "volume": 88,
    "start": "2025-12-24T09:09:00.000Z",
    "end": "2025-12-24T09:10:00.000Z"
  },
  {
    "symbol": "UNH",
    "timeframe": "1m",
    "open": 324.51,
    "high": 324.51,
    "low": 324.51,
    "close": 324.51,
    "volume": 74,
    "start": "2025-12-24T09:16:00.000Z",
    "end": "2025-12-24T09:17:00.000Z"
  },
  {
    "symbol": "UNH",
    "timeframe": "1m",
    "open": 324.7,
    "high": 324.7,
    "low": 324.7,
    "close": 324.7,
    "volume": 203,
    "start": "2025-12-24T09:29:00.000Z",
    "end": "2025-12-24T09:30:00.000Z"
  },
  {
    "symbol": "UNH",
    "timeframe": "1m",
    "open": 324.65,
    "high": 324.65,
    "low": 324.65,
    "close": 324.65,
    "volume": 50,
    "start": "2025-12-24T09:47:00.000Z",
    "end": "2025-12-24T09:48:00.000Z"
  },
  {
    "symbol": "UNH",
    "timeframe": "1m",
    "open": 324.66,
    "high": 324.66,
    "low": 324.66,
    "close": 324.66,
    "volume": 44,
    "start": "2025-12-24T10:14:00.000Z",
    "end": "2025-12-24T10:15:00.000Z"
  },
  {
    "symbol": "UNH",
    "timeframe": "1m",
    "open": 324.51,
    "high": 324.51,
    "low": 324.51,
    "close": 324.51,
    "volume": 158,
    "start": "2025-12-24T10:16:00.000Z",
    "end": "2025-12-24T10:17:00.000Z"
  },
  {
    "symbol": "UNH",
    "timeframe": "1m",
    "open": 324.5,
    "high": 324.5,
    "low": 324.5,
    "close": 324.5,
    "volume": 64,
    "start": "2025-12-24T10:17:00.000Z",
    "end": "2025-12-24T10:18:00.000Z"
  },
  {
    "symbol": "UNH",
    "timeframe": "1m",
    "open": 324.6,
    "high": 324.6,
    "low": 324.6,
    "close": 324.6,
    "volume": 53,
    "start": "2025-12-24T10:19:00.000Z",
    "end": "2025-12-24T10:20:00.000Z"
  },
  {
    "symbol": "UNH",
    "timeframe": "1m",
    "open": 324.6,
    "high": 324.6,
    "low": 324.6,
    "close": 324.6,
    "volume": 290,
    "start": "2025-12-24T10:56:00.000Z",
    "end": "2025-12-24T10:57:00.000Z"
  },
  {
    "symbol": "UNH",
    "timeframe": "1m",
    "open": 324.72,
    "high": 324.72,
    "low": 324.72,
    "close": 324.72,
    "volume": 206,
    "start": "2025-12-24T11:16:00.000Z",
    "end": "2025-12-24T11:17:00.000Z"
  },
  {
    "symbol": "UNH",
    "timeframe": "1m",
    "open": 324.54,
    "high": 324.54,
    "low": 324.54,
    "close": 324.54,
    "volume": 85,
    "start": "2025-12-24T11:45:00.000Z",
    "end": "2025-12-24T11:46:00.000Z"
  },
  {
    "symbol": "UNH",
    "timeframe": "1m",
    "open": 324.45,
    "high": 324.45,
    "low": 324.45,
    "close": 324.45,
    "volume": 157,
    "start": "2025-12-24T11:50:00.000Z",
    "end": "2025-12-24T11:51:00.000Z"
  },
  {
    "symbol": "UNH",
    "timeframe": "1m",
    "open": 324.5,
    "high": 324.5,
    "low": 324.45,
    "close": 324.5,
    "volume": 538,
    "start": "2025-12-24T12:00:00.000Z",
    "end": "2025-12-24T12:01:00.000Z"
  },
  {
    "symbol": "UNH",
    "timeframe": "1m",
    "open": 324.55,
    "high": 324.55,
    "low": 324.55,
    "close": 324.55,
    "volume": 46,
    "start": "2025-12-24T12:04:00.000Z",
    "end": "2025-12-24T12:05:00.000Z"
  },
  {
    "symbol": "UNH",
    "timeframe": "1m",
    "open": 324.69,
    "high": 324.69,
    "low": 324.69,
    "close": 324.69,
    "volume": 127,
    "start": "2025-12-24T12:14:00.000Z",
    "end": "2025-12-24T12:15:00.000Z"
  },
  {
    "symbol": "UNH",
    "timeframe": "1m",
    "open": 324.73,
    "high": 324.75,
    "low": 324.69,
    "close": 324.75,
    "volume": 1530,
    "start": "2025-12-24T12:16:00.000Z",
    "end": "2025-12-24T12:17:00.000Z"
  },
  {
    "symbol": "UNH",
    "timeframe": "1m",
    "open": 324.88,
    "high": 324.88,
    "low": 324.73,
    "close": 324.74,
    "volume": 1090,
    "start": "2025-12-24T12:23:00.000Z",
    "end": "2025-12-24T12:24:00.000Z"
  },
  {
    "symbol": "UNH",
    "timeframe": "1m",
    "open": 324.7,
    "high": 324.7,
    "low": 324.7,
    "close": 324.7,
    "volume": 83,
    "start": "2025-12-24T12:24:00.000Z",
    "end": "2025-12-24T12:25:00.000Z"
  },
  {
    "symbol": "UNH",
    "timeframe": "1m",
    "open": 324.74,
    "high": 324.74,
    "low": 324.73,
    "close": 324.73,
    "volume": 1251,
    "start": "2025-12-24T12:25:00.000Z",
    "end": "2025-12-24T12:26:00.000Z"
  },
  {
    "symbol": "UNH",
    "timeframe": "1m",
    "open": 324.73,
    "high": 324.73,
    "low": 324.73,
    "close": 324.73,
    "volume": 237,
    "start": "2025-12-24T12:28:00.000Z",
    "end": "2025-12-24T12:29:00.000Z"
  },
  {
    "symbol": "UNH",
    "timeframe": "1m",
    "open": 324.81,
    "high": 324.81,
    "low": 324.81,
    "close": 324.81,
    "volume": 177,
    "start": "2025-12-24T12:39:00.000Z",
    "end": "2025-12-24T12:40:00.000Z"
  },
  {
    "symbol": "UNH",
    "timeframe": "1m",
    "open": 324.75,
    "high": 324.75,
    "low": 324.75,
    "close": 324.75,
    "volume": 494,
    "start": "2025-12-24T12:40:00.000Z",
    "end": "2025-12-24T12:41:00.000Z"
  },
  {
    "symbol": "UNH",
    "timeframe": "1m",
    "open": 324.73,
    "high": 324.75,
    "low": 324.72,
    "close": 324.75,
    "volume": 982,
    "start": "2025-12-24T12:41:00.000Z",
    "end": "2025-12-24T12:42:00.000Z"
  },
  {
    "symbol": "UNH",
    "timeframe": "1m",
    "open": 324.7,
    "high": 324.7,
    "low": 324.7,
    "close": 324.7,
    "volume": 172,
    "start": "2025-12-24T12:48:00.000Z",
    "end": "2025-12-24T12:49:00.000Z"
  },
  {
    "symbol": "UNH",
    "timeframe": "1m",
    "open": 324.68,
    "high": 324.68,
    "low": 324.68,
    "close": 324.68,
    "volume": 44,
    "start": "2025-12-24T12:56:00.000Z",
    "end": "2025-12-24T12:57:00.000Z"
  },
  {
    "symbol": "UNH",
    "timeframe": "1m",
    "open": 324.6,
    "high": 324.91,
    "low": 324.45,
    "close": 324.5,
    "volume": 10692,
    "start": "2025-12-24T13:00:00.000Z",
    "end": "2025-12-24T13:01:00.000Z"
  },
  {
    "symbol": "UNH",
    "timeframe": "1m",
    "open": 324.78,
    "high": 324.78,
    "low": 324.78,
    "close": 324.78,
    "volume": 656,
    "start": "2025-12-24T13:01:00.000Z",
    "end": "2025-12-24T13:02:00.000Z"
  },
  {
    "symbol": "UNH",
    "timeframe": "1m",
    "open": 324.61,
    "high": 324.61,
    "low": 324.61,
    "close": 324.61,
    "volume": 370,
    "start": "2025-12-24T13:03:00.000Z",
    "end": "2025-12-24T13:04:00.000Z"
  },
  {
    "symbol": "UNH",
    "timeframe": "1m",
    "open": 324.73,
    "high": 324.82,
    "low": 324.73,
    "close": 324.82,
    "volume": 692,
    "start": "2025-12-24T13:06:00.000Z",
    "end": "2025-12-24T13:07:00.000Z"
  },
  {
    "symbol": "UNH",
    "timeframe": "1m",
    "open": 324.78,
    "high": 324.78,
    "low": 324.78,
    "close": 324.78,
    "volume": 172,
    "start": "2025-12-24T13:10:00.000Z",
    "end": "2025-12-24T13:11:00.000Z"
  },
  {
    "symbol": "UNH",
    "timeframe": "1m",
    "open": 324.8,
    "high": 324.8,
    "low": 324.8,
    "close": 324.8,
    "volume": 128,
    "start": "2025-12-24T13:20:00.000Z",
    "end": "2025-12-24T13:21:00.000Z"
  },
  {
    "symbol": "UNH",
    "timeframe": "1m",
    "open": 324.85,
    "high": 324.93,
    "low": 324.85,
    "close": 324.93,
    "volume": 1447,
    "start": "2025-12-24T13:24:00.000Z",
    "end": "2025-12-24T13:25:00.000Z"
  },
  {
    "symbol": "UNH",
    "timeframe": "1m",
    "open": 324.9,
    "high": 324.9,
    "low": 324.9,
    "close": 324.9,
    "volume": 74,
    "start": "2025-12-24T13:27:00.000Z",
    "end": "2025-12-24T13:28:00.000Z"
  },
  {
    "symbol": "UNH",
    "timeframe": "1m",
    "open": 325,
    "high": 325,
    "low": 325,
    "close": 325,
    "volume": 136,
    "start": "2025-12-24T13:28:00.000Z",
    "end": "2025-12-24T13:29:00.000Z"
  },
  {
    "symbol": "UNH",
    "timeframe": "1m",
    "open": 325.0984,
    "high": 325.1,
    "low": 325.0984,
    "close": 325.1,
    "volume": 455,
    "start": "2025-12-24T13:29:00.000Z",
    "end": "2025-12-24T13:30:00.000Z"
  },
  {
    "symbol": "UNH",
    "timeframe": "1m",
    "open": 325.1,
    "high": 325.1,
    "low": 325.1,
    "close": 325.1,
    "volume": 560,
    "start": "2025-12-24T13:30:00.000Z",
    "end": "2025-12-24T13:31:00.000Z"
  },
  {
    "symbol": "UNH",
    "timeframe": "1m",
    "open": 324.99,
    "high": 325,
    "low": 324.99,
    "close": 325,
    "volume": 245,
    "start": "2025-12-24T13:31:00.000Z",
    "end": "2025-12-24T13:32:00.000Z"
  },
  {
    "symbol": "UNH",
    "timeframe": "1m",
    "open": 325.01,
    "high": 325.01,
    "low": 325,
    "close": 325,
    "volume": 229,
    "start": "2025-12-24T13:33:00.000Z",
    "end": "2025-12-24T13:34:00.000Z"
  },
  {
    "symbol": "UNH",
    "timeframe": "1m",
    "open": 325,
    "high": 325,
    "low": 325,
    "close": 325,
    "volume": 167,
    "start": "2025-12-24T13:36:00.000Z",
    "end": "2025-12-24T13:37:00.000Z"
  },
  {
    "symbol": "UNH",
    "timeframe": "1m",
    "open": 324.98,
    "high": 324.98,
    "low": 324.98,
    "close": 324.98,
    "volume": 123,
    "start": "2025-12-24T13:37:00.000Z",
    "end": "2025-12-24T13:38:00.000Z"
  },
  {
    "symbol": "UNH",
    "timeframe": "1m",
    "open": 325,
    "high": 325,
    "low": 325,
    "close": 325,
    "volume": 202,
    "start": "2025-12-24T13:39:00.000Z",
    "end": "2025-12-24T13:40:00.000Z"
  },
  {
    "symbol": "UNH",
    "timeframe": "1m",
    "open": 324.95,
    "high": 324.95,
    "low": 324.95,
    "close": 324.95,
    "volume": 122,
    "start": "2025-12-24T13:42:00.000Z",
    "end": "2025-12-24T13:43:00.000Z"
  },
  {
    "symbol": "UNH",
    "timeframe": "1m",
    "open": 325,
    "high": 325,
    "low": 325,
    "close": 325,
    "volume": 109,
    "start": "2025-12-24T13:43:00.000Z",
    "end": "2025-12-24T13:44:00.000Z"
  },
  {
    "symbol": "UNH",
    "timeframe": "1m",
    "open": 324.92,
    "high": 324.92,
    "low": 324.92,
    "close": 324.92,
    "volume": 95,
    "start": "2025-12-24T13:48:00.000Z",
    "end": "2025-12-24T13:49:00.000Z"
  },
  {
    "symbol": "UNH",
    "timeframe": "1m",
    "open": 324.95,
    "high": 324.95,
    "low": 324.95,
    "close": 324.95,
    "volume": 115,
    "start": "2025-12-24T13:50:00.000Z",
    "end": "2025-12-24T13:51:00.000Z"
  },
  {
    "symbol": "UNH",
    "timeframe": "1m",
    "open": 324.95,
    "high": 325,
    "low": 324.95,
    "close": 325,
    "volume": 452,
    "start": "2025-12-24T13:52:00.000Z",
    "end": "2025-12-24T13:53:00.000Z"
  },
  {
    "symbol": "UNH",
    "timeframe": "1m",
    "open": 325,
    "high": 325,
    "low": 325,
    "close": 325,
    "volume": 71,
    "start": "2025-12-24T13:53:00.000Z",
    "end": "2025-12-24T13:54:00.000Z"
  },
  {
    "symbol": "UNH",
    "timeframe": "1m",
    "open": 325.08,
    "high": 325.08,
    "low": 325.08,
    "close": 325.08,
    "volume": 63,
    "start": "2025-12-24T13:56:00.000Z",
    "end": "2025-12-24T13:57:00.000Z"
  },
  {
    "symbol": "UNH",
    "timeframe": "1m",
    "open": 324.94,
    "high": 324.94,
    "low": 324.94,
    "close": 324.94,
    "volume": 110,
    "start": "2025-12-24T13:58:00.000Z",
    "end": "2025-12-24T13:59:00.000Z"
  },
  {
    "symbol": "UNH",
    "timeframe": "1m",
    "open": 325.03,
    "high": 325.03,
    "low": 325.03,
    "close": 325.03,
    "volume": 76,
    "start": "2025-12-24T14:00:00.000Z",
    "end": "2025-12-24T14:01:00.000Z"
  },
  {
    "symbol": "UNH",
    "timeframe": "1m",
    "open": 324.94,
    "high": 324.94,
    "low": 324.94,
    "close": 324.94,
    "volume": 127,
    "start": "2025-12-24T14:03:00.000Z",
    "end": "2025-12-24T14:04:00.000Z"
  },
  {
    "symbol": "UNH",
    "timeframe": "1m",
    "open": 324.95,
    "high": 324.97,
    "low": 324.95,
    "close": 324.97,
    "volume": 359,
    "start": "2025-12-24T14:04:00.000Z",
    "end": "2025-12-24T14:05:00.000Z"
  },
  {
    "symbol": "UNH",
    "timeframe": "1m",
    "open": 324.98,
    "high": 325,
    "low": 324.98,
    "close": 325,
    "volume": 550,
    "start": "2025-12-24T14:05:00.000Z",
    "end": "2025-12-24T14:06:00.000Z"
  },
  {
    "symbol": "UNH",
    "timeframe": "1m",
    "open": 325.09,
    "high": 325.1,
    "low": 324.91,
    "close": 324.91,
    "volume": 833,
    "start": "2025-12-24T14:08:00.000Z",
    "end": "2025-12-24T14:09:00.000Z"
  },
  {
    "symbol": "UNH",
    "timeframe": "1m",
    "open": 325.07,
    "high": 325.07,
    "low": 325.07,
    "close": 325.07,
    "volume": 96,
    "start": "2025-12-24T14:09:00.000Z",
    "end": "2025-12-24T14:10:00.000Z"
  },
  {
    "symbol": "UNH",
    "timeframe": "1m",
    "open": 325,
    "high": 325,
    "low": 325,
    "close": 325,
    "volume": 154,
    "start": "2025-12-24T14:10:00.000Z",
    "end": "2025-12-24T14:11:00.000Z"
  },
  {
    "symbol": "UNH",
    "timeframe": "1m",
    "open": 325.05,
    "high": 325.05,
    "low": 325.05,
    "close": 325.05,
    "volume": 132,
    "start": "2025-12-24T14:12:00.000Z",
    "end": "2025-12-24T14:13:00.000Z"
  },
  {
    "symbol": "UNH",
    "timeframe": "1m",
    "open": 325.1,
    "high": 325.1,
    "low": 325.1,
    "close": 325.1,
    "volume": 105,
    "start": "2025-12-24T14:15:00.000Z",
    "end": "2025-12-24T14:16:00.000Z"
  },
  {
    "symbol": "UNH",
    "timeframe": "1m",
    "open": 325.05,
    "high": 325.05,
    "low": 325.05,
    "close": 325.05,
    "volume": 346,
    "start": "2025-12-24T14:17:00.000Z",
    "end": "2025-12-24T14:18:00.000Z"
  },
  {
    "symbol": "UNH",
    "timeframe": "1m",
    "open": 325.02,
    "high": 325.02,
    "low": 325.02,
    "close": 325.02,
    "volume": 409,
    "start": "2025-12-24T14:19:00.000Z",
    "end": "2025-12-24T14:20:00.000Z"
  },
  {
    "symbol": "UNH",
    "timeframe": "1m",
    "open": 325.02,
    "high": 325.02,
    "low": 325,
    "close": 325,
    "volume": 425,
    "start": "2025-12-24T14:20:00.000Z",
    "end": "2025-12-24T14:21:00.000Z"
  },
  {
    "symbol": "UNH",
    "timeframe": "1m",
    "open": 324.93,
    "high": 324.93,
    "low": 324.9,
    "close": 324.9,
    "volume": 858,
    "start": "2025-12-24T14:21:00.000Z",
    "end": "2025-12-24T14:22:00.000Z"
  },
  {
    "symbol": "UNH",
    "timeframe": "1m",
    "open": 324.88,
    "high": 324.88,
    "low": 324.88,
    "close": 324.88,
    "volume": 237,
    "start": "2025-12-24T14:22:00.000Z",
    "end": "2025-12-24T14:23:00.000Z"
  },
  {
    "symbol": "UNH",
    "timeframe": "1m",
    "open": 324.84,
    "high": 324.84,
    "low": 324.84,
    "close": 324.84,
    "volume": 303,
    "start": "2025-12-24T14:23:00.000Z",
    "end": "2025-12-24T14:24:00.000Z"
  },
  {
    "symbol": "UNH",
    "timeframe": "1m",
    "open": 324.81,
    "high": 324.81,
    "low": 324.81,
    "close": 324.81,
    "volume": 92,
    "start": "2025-12-24T14:24:00.000Z",
    "end": "2025-12-24T14:25:00.000Z"
  },
  {
    "symbol": "UNH",
    "timeframe": "1m",
    "open": 324.84,
    "high": 324.84,
    "low": 324.81,
    "close": 324.81,
    "volume": 571,
    "start": "2025-12-24T14:25:00.000Z",
    "end": "2025-12-24T14:26:00.000Z"
  },
  {
    "symbol": "UNH",
    "timeframe": "1m",
    "open": 324.89,
    "high": 324.94,
    "low": 324.89,
    "close": 324.89,
    "volume": 231,
    "start": "2025-12-24T14:26:00.000Z",
    "end": "2025-12-24T14:27:00.000Z"
  },
  {
    "symbol": "UNH",
    "timeframe": "1m",
    "open": 324.71,
    "high": 324.73,
    "low": 324.7,
    "close": 324.71,
    "volume": 658,
    "start": "2025-12-24T14:28:00.000Z",
    "end": "2025-12-24T14:29:00.000Z"
  },
  {
    "symbol": "UNH",
    "timeframe": "1m",
    "open": 324.9094,
    "high": 324.93,
    "low": 324.9094,
    "close": 324.93,
    "volume": 346,
    "start": "2025-12-24T14:29:00.000Z",
    "end": "2025-12-24T14:30:00.000Z"
  },
  {
    "symbol": "UNH",
    "timeframe": "1m",
    "open": 325.2,
    "high": 325.32,
    "low": 324.13,
    "close": 324.21,
    "volume": 74945,
    "start": "2025-12-24T14:30:00.000Z",
    "end": "2025-12-24T14:31:00.000Z"
  },
  {
    "symbol": "UNH",
    "timeframe": "1m",
    "open": 324.545,
    "high": 325.82,
    "low": 324.545,
    "close": 325.7,
    "volume": 14617,
    "start": "2025-12-24T14:31:00.000Z",
    "end": "2025-12-24T14:32:00.000Z"
  },
  {
    "symbol": "UNH",
    "timeframe": "1m",
    "open": 325.7,
    "high": 326.1675,
    "low": 325.6,
    "close": 325.9224,
    "volume": 19199,
    "start": "2025-12-24T14:32:00.000Z",
    "end": "2025-12-24T14:33:00.000Z"
  },
  {
    "symbol": "UNH",
    "timeframe": "1m",
    "open": 325.98,
    "high": 326.45,
    "low": 325.62,
    "close": 326.23,
    "volume": 22782,
    "start": "2025-12-24T14:33:00.000Z",
    "end": "2025-12-24T14:34:00.000Z"
  },
  {
    "symbol": "UNH",
    "timeframe": "1m",
    "open": 326.01,
    "high": 326.4348,
    "low": 326,
    "close": 326.345,
    "volume": 24782,
    "start": "2025-12-24T14:34:00.000Z",
    "end": "2025-12-24T14:35:00.000Z"
  },
  {
    "symbol": "UNH",
    "timeframe": "1m",
    "open": 326.33,
    "high": 326.64,
    "low": 326.05,
    "close": 326.15,
    "volume": 21694,
    "start": "2025-12-24T14:35:00.000Z",
    "end": "2025-12-24T14:36:00.000Z"
  },
  {
    "symbol": "UNH",
    "timeframe": "1m",
    "open": 326.1,
    "high": 326.8,
    "low": 326.1,
    "close": 326.67,
    "volume": 19697,
    "start": "2025-12-24T14:36:00.000Z",
    "end": "2025-12-24T14:37:00.000Z"
  },
  {
    "symbol": "UNH",
    "timeframe": "1m",
    "open": 326.85,
    "high": 327.14,
    "low": 326.66,
    "close": 327.0462,
    "volume": 20673,
    "start": "2025-12-24T14:37:00.000Z",
    "end": "2025-12-24T14:38:00.000Z"
  },
  {
    "symbol": "UNH",
    "timeframe": "1m",
    "open": 327.0412,
    "high": 327.29,
    "low": 326.55,
    "close": 326.5601,
    "volume": 26959,
    "start": "2025-12-24T14:38:00.000Z",
    "end": "2025-12-24T14:39:00.000Z"
  },
  {
    "symbol": "UNH",
    "timeframe": "1m",
    "open": 326.725,
    "high": 326.75,
    "low": 326.31,
    "close": 326.75,
    "volume": 6188,
    "start": "2025-12-24T14:39:00.000Z",
    "end": "2025-12-24T14:40:00.000Z"
  },
  {
    "symbol": "UNH",
    "timeframe": "1m",
    "open": 326.7281,
    "high": 326.75,
    "low": 326.2501,
    "close": 326.355,
    "volume": 7774,
    "start": "2025-12-24T14:40:00.000Z",
    "end": "2025-12-24T14:41:00.000Z"
  },
  {
    "symbol": "UNH",
    "timeframe": "1m",
    "open": 326.26,
    "high": 326.85,
    "low": 326.2,
    "close": 326.74,
    "volume": 12570,
    "start": "2025-12-24T14:41:00.000Z",
    "end": "2025-12-24T14:42:00.000Z"
  },
  {
    "symbol": "UNH",
    "timeframe": "1m",
    "open": 326.87,
    "high": 327.23,
    "low": 326.8,
    "close": 327.1,
    "volume": 14240,
    "start": "2025-12-24T14:42:00.000Z",
    "end": "2025-12-24T14:43:00.000Z"
  },
  {
    "symbol": "UNH",
    "timeframe": "1m",
    "open": 327.1,
    "high": 327.27,
    "low": 326.76,
    "close": 327.1159,
    "volume": 14984,
    "start": "2025-12-24T14:43:00.000Z",
    "end": "2025-12-24T14:44:00.000Z"
  },
  {
    "symbol": "UNH",
    "timeframe": "1m",
    "open": 327.11,
    "high": 327.28,
    "low": 326.7401,
    "close": 327.1801,
    "volume": 17208,
    "start": "2025-12-24T14:44:00.000Z",
    "end": "2025-12-24T14:45:00.000Z"
  },
  {
    "symbol": "UNH",
    "timeframe": "1m",
    "open": 327.1835,
    "high": 327.59,
    "low": 326.94,
    "close": 326.9438,
    "volume": 15428,
    "start": "2025-12-24T14:45:00.000Z",
    "end": "2025-12-24T14:46:00.000Z"
  },
  {
    "symbol": "UNH",
    "timeframe": "1m",
    "open": 326.85,
    "high": 327,
    "low": 326.76,
    "close": 326.835,
    "volume": 6742,
    "start": "2025-12-24T14:46:00.000Z",
    "end": "2025-12-24T14:47:00.000Z"
  },
  {
    "symbol": "UNH",
    "timeframe": "1m",
    "open": 326.92,
    "high": 326.98,
    "low": 326.45,
    "close": 326.464,
    "volume": 6883,
    "start": "2025-12-24T14:47:00.000Z",
    "end": "2025-12-24T14:48:00.000Z"
  },
  {
    "symbol": "UNH",
    "timeframe": "1m",
    "open": 326.5,
    "high": 326.55,
    "low": 326.23,
    "close": 326.35,
    "volume": 10733,
    "start": "2025-12-24T14:48:00.000Z",
    "end": "2025-12-24T14:49:00.000Z"
  },
  {
    "symbol": "UNH",
    "timeframe": "1m",
    "open": 326.2211,
    "high": 326.3,
    "low": 325.91,
    "close": 325.96,
    "volume": 18000,
    "start": "2025-12-24T14:49:00.000Z",
    "end": "2025-12-24T14:50:00.000Z"
  },
  {
    "symbol": "UNH",
    "timeframe": "1m",
    "open": 325.95,
    "high": 326.02,
    "low": 325.5,
    "close": 325.97,
    "volume": 12051,
    "start": "2025-12-24T14:50:00.000Z",
    "end": "2025-12-24T14:51:00.000Z"
  },
  {
    "symbol": "UNH",
    "timeframe": "1m",
    "open": 325.94,
    "high": 326.1283,
    "low": 325.88,
    "close": 326.1283,
    "volume": 9300,
    "start": "2025-12-24T14:51:00.000Z",
    "end": "2025-12-24T14:52:00.000Z"
  },
  {
    "symbol": "UNH",
    "timeframe": "1m",
    "open": 326.105,
    "high": 326.105,
    "low": 325.59,
    "close": 325.76,
    "volume": 5021,
    "start": "2025-12-24T14:52:00.000Z",
    "end": "2025-12-24T14:53:00.000Z"
  },
  {
    "symbol": "UNH",
    "timeframe": "1m",
    "open": 325.8,
    "high": 325.85,
    "low": 325.7,
    "close": 325.83,
    "volume": 5910,
    "start": "2025-12-24T14:53:00.000Z",
    "end": "2025-12-24T14:54:00.000Z"
  },
  {
    "symbol": "UNH",
    "timeframe": "1m",
    "open": 325.815,
    "high": 325.85,
    "low": 325.61,
    "close": 325.765,
    "volume": 8343,
    "start": "2025-12-24T14:54:00.000Z",
    "end": "2025-12-24T14:55:00.000Z"
  },
  {
    "symbol": "UNH",
    "timeframe": "1m",
    "open": 325.7815,
    "high": 325.7815,
    "low": 325.5522,
    "close": 325.574,
    "volume": 8080,
    "start": "2025-12-24T14:55:00.000Z",
    "end": "2025-12-24T14:56:00.000Z"
  },
  {
    "symbol": "UNH",
    "timeframe": "1m",
    "open": 325.56,
    "high": 325.67,
    "low": 325.26,
    "close": 325.36,
    "volume": 8872,
    "start": "2025-12-24T14:56:00.000Z",
    "end": "2025-12-24T14:57:00.000Z"
  },
  {
    "symbol": "UNH",
    "timeframe": "1m",
    "open": 325.3,
    "high": 325.49,
    "low": 325.2,
    "close": 325.305,
    "volume": 10486,
    "start": "2025-12-24T14:57:00.000Z",
    "end": "2025-12-24T14:58:00.000Z"
  },
  {
    "symbol": "UNH",
    "timeframe": "1m",
    "open": 325.3,
    "high": 325.469,
    "low": 325.26,
    "close": 325.43,
    "volume": 4557,
    "start": "2025-12-24T14:58:00.000Z",
    "end": "2025-12-24T14:59:00.000Z"
  },
  {
    "symbol": "UNH",
    "timeframe": "1m",
    "open": 325.3737,
    "high": 325.43,
    "low": 325.2801,
    "close": 325.34,
    "volume": 11378,
    "start": "2025-12-24T14:59:00.000Z",
    "end": "2025-12-24T15:00:00.000Z"
  },
  {
    "symbol": "UNH",
    "timeframe": "1m",
    "open": 325.26,
    "high": 325.452,
    "low": 325.24,
    "close": 325.33,
    "volume": 6329,
    "start": "2025-12-24T15:00:00.000Z",
    "end": "2025-12-24T15:01:00.000Z"
  },
  {
    "symbol": "UNH",
    "timeframe": "1m",
    "open": 325.3,
    "high": 325.47,
    "low": 325.22,
    "close": 325.385,
    "volume": 4627,
    "start": "2025-12-24T15:01:00.000Z",
    "end": "2025-12-24T15:02:00.000Z"
  },
  {
    "symbol": "UNH",
    "timeframe": "1m",
    "open": 325.425,
    "high": 325.72,
    "low": 325.425,
    "close": 325.595,
    "volume": 17012,
    "start": "2025-12-24T15:02:00.000Z",
    "end": "2025-12-24T15:03:00.000Z"
  },
  {
    "symbol": "UNH",
    "timeframe": "1m",
    "open": 325.595,
    "high": 325.64,
    "low": 325.4,
    "close": 325.4,
    "volume": 5882,
    "start": "2025-12-24T15:03:00.000Z",
    "end": "2025-12-24T15:04:00.000Z"
  },
  {
    "symbol": "UNH",
    "timeframe": "1m",
    "open": 325.475,
    "high": 325.475,
    "low": 324.93,
    "close": 325.01,
    "volume": 25460,
    "start": "2025-12-24T15:04:00.000Z",
    "end": "2025-12-24T15:05:00.000Z"
  },
  {
    "symbol": "UNH",
    "timeframe": "1m",
    "open": 324.97,
    "high": 325.13,
    "low": 324.8,
    "close": 325.005,
    "volume": 8416,
    "start": "2025-12-24T15:05:00.000Z",
    "end": "2025-12-24T15:06:00.000Z"
  },
  {
    "symbol": "UNH",
    "timeframe": "1m",
    "open": 325.0237,
    "high": 325.05,
    "low": 324.81,
    "close": 324.97,
    "volume": 16832,
    "start": "2025-12-24T15:06:00.000Z",
    "end": "2025-12-24T15:07:00.000Z"
  },
  {
    "symbol": "UNH",
    "timeframe": "1m",
    "open": 324.9922,
    "high": 325.34,
    "low": 324.9922,
    "close": 325.31,
    "volume": 6410,
    "start": "2025-12-24T15:07:00.000Z",
    "end": "2025-12-24T15:08:00.000Z"
  },
  {
    "symbol": "UNH",
    "timeframe": "1m",
    "open": 325.3,
    "high": 325.42,
    "low": 325.18,
    "close": 325.18,
    "volume": 4720,
    "start": "2025-12-24T15:08:00.000Z",
    "end": "2025-12-24T15:09:00.000Z"
  },
  {
    "symbol": "UNH",
    "timeframe": "1m",
    "open": 325.18,
    "high": 325.31,
    "low": 325.0618,
    "close": 325.135,
    "volume": 3052,
    "start": "2025-12-24T15:09:00.000Z",
    "end": "2025-12-24T15:10:00.000Z"
  },
  {
    "symbol": "UNH",
    "timeframe": "1m",
    "open": 325.23,
    "high": 325.45,
    "low": 325.1712,
    "close": 325.22,
    "volume": 4801,
    "start": "2025-12-24T15:10:00.000Z",
    "end": "2025-12-24T15:11:00.000Z"
  },
  {
    "symbol": "UNH",
    "timeframe": "1m",
    "open": 325.2513,
    "high": 325.3,
    "low": 325.125,
    "close": 325.22,
    "volume": 3558,
    "start": "2025-12-24T15:11:00.000Z",
    "end": "2025-12-24T15:12:00.000Z"
  },
  {
    "symbol": "UNH",
    "timeframe": "1m",
    "open": 325.155,
    "high": 325.36,
    "low": 325.155,
    "close": 325.1665,
    "volume": 5141,
    "start": "2025-12-24T15:12:00.000Z",
    "end": "2025-12-24T15:13:00.000Z"
  },
  {
    "symbol": "UNH",
    "timeframe": "1m",
    "open": 325.18,
    "high": 325.58,
    "low": 325.18,
    "close": 325.415,
    "volume": 7882,
    "start": "2025-12-24T15:13:00.000Z",
    "end": "2025-12-24T15:14:00.000Z"
  },
  {
    "symbol": "UNH",
    "timeframe": "1m",
    "open": 325.45,
    "high": 325.5899,
    "low": 325.31,
    "close": 325.5658,
    "volume": 3295,
    "start": "2025-12-24T15:14:00.000Z",
    "end": "2025-12-24T15:15:00.000Z"
  },
  {
    "symbol": "UNH",
    "timeframe": "1m",
    "open": 325.57,
    "high": 325.775,
    "low": 325.5207,
    "close": 325.775,
    "volume": 11380,
    "start": "2025-12-24T15:15:00.000Z",
    "end": "2025-12-24T15:16:00.000Z"
  },
  {
    "symbol": "UNH",
    "timeframe": "1m",
    "open": 325.775,
    "high": 325.83,
    "low": 325.7,
    "close": 325.8,
    "volume": 4925,
    "start": "2025-12-24T15:16:00.000Z",
    "end": "2025-12-24T15:17:00.000Z"
  },
  {
    "symbol": "UNH",
    "timeframe": "1m",
    "open": 325.755,
    "high": 325.8,
    "low": 325.52,
    "close": 325.61,
    "volume": 5656,
    "start": "2025-12-24T15:17:00.000Z",
    "end": "2025-12-24T15:18:00.000Z"
  },
  {
    "symbol": "UNH",
    "timeframe": "1m",
    "open": 325.61,
    "high": 325.6497,
    "low": 325.52,
    "close": 325.55,
    "volume": 5993,
    "start": "2025-12-24T15:18:00.000Z",
    "end": "2025-12-24T15:19:00.000Z"
  },
  {
    "symbol": "UNH",
    "timeframe": "1m",
    "open": 325.56,
    "high": 325.65,
    "low": 325.52,
    "close": 325.6,
    "volume": 49424,
    "start": "2025-12-24T15:19:00.000Z",
    "end": "2025-12-24T15:20:00.000Z"
  },
  {
    "symbol": "UNH",
    "timeframe": "1m",
    "open": 325.67,
    "high": 325.8,
    "low": 325.65,
    "close": 325.7999,
    "volume": 4924,
    "start": "2025-12-24T15:20:00.000Z",
    "end": "2025-12-24T15:21:00.000Z"
  },
  {
    "symbol": "UNH",
    "timeframe": "1m",
    "open": 325.75,
    "high": 325.92,
    "low": 325.655,
    "close": 325.775,
    "volume": 170132,
    "start": "2025-12-24T15:21:00.000Z",
    "end": "2025-12-24T15:22:00.000Z"
  },
  {
    "symbol": "UNH",
    "timeframe": "1m",
    "open": 325.775,
    "high": 326.17,
    "low": 325.511,
    "close": 325.665,
    "volume": 7165,
    "start": "2025-12-24T15:22:00.000Z",
    "end": "2025-12-24T15:23:00.000Z"
  },
  {
    "symbol": "UNH",
    "timeframe": "1m",
    "open": 325.51,
    "high": 325.79,
    "low": 325.51,
    "close": 325.7225,
    "volume": 4121,
    "start": "2025-12-24T15:23:00.000Z",
    "end": "2025-12-24T15:24:00.000Z"
  },
  {
    "symbol": "UNH",
    "timeframe": "1m",
    "open": 325.74,
    "high": 326,
    "low": 325.74,
    "close": 325.98,
    "volume": 108326,
    "start": "2025-12-24T15:24:00.000Z",
    "end": "2025-12-24T15:25:00.000Z"
  },
  {
    "symbol": "UNH",
    "timeframe": "1m",
    "open": 326,
    "high": 326.29,
    "low": 325.81,
    "close": 326.26,
    "volume": 5526,
    "start": "2025-12-24T15:25:00.000Z",
    "end": "2025-12-24T15:26:00.000Z"
  },
  {
    "symbol": "UNH",
    "timeframe": "1m",
    "open": 326.195,
    "high": 326.6958,
    "low": 326.0952,
    "close": 326.55,
    "volume": 13137,
    "start": "2025-12-24T15:26:00.000Z",
    "end": "2025-12-24T15:27:00.000Z"
  },
  {
    "symbol": "UNH",
    "timeframe": "1m",
    "open": 326.55,
    "high": 326.79,
    "low": 326.46,
    "close": 326.51,
    "volume": 17074,
    "start": "2025-12-24T15:27:00.000Z",
    "end": "2025-12-24T15:28:00.000Z"
  },
  {
    "symbol": "UNH",
    "timeframe": "1m",
    "open": 326.5175,
    "high": 326.82,
    "low": 326.5175,
    "close": 326.61,
    "volume": 11211,
    "start": "2025-12-24T15:28:00.000Z",
    "end": "2025-12-24T15:29:00.000Z"
  },
  {
    "symbol": "UNH",
    "timeframe": "1m",
    "open": 326.74,
    "high": 326.88,
    "low": 326.6101,
    "close": 326.82,
    "volume": 10009,
    "start": "2025-12-24T15:29:00.000Z",
    "end": "2025-12-24T15:30:00.000Z"
  },
  {
    "symbol": "UNH",
    "timeframe": "1m",
    "open": 326.8,
    "high": 327.2,
    "low": 326.78,
    "close": 327.1285,
    "volume": 19802,
    "start": "2025-12-24T15:30:00.000Z",
    "end": "2025-12-24T15:31:00.000Z"
  },
  {
    "symbol": "UNH",
    "timeframe": "1m",
    "open": 327.115,
    "high": 327.46,
    "low": 327.0456,
    "close": 327.1384,
    "volume": 26646,
    "start": "2025-12-24T15:31:00.000Z",
    "end": "2025-12-24T15:32:00.000Z"
  },
  {
    "symbol": "UNH",
    "timeframe": "1m",
    "open": 327.2,
    "high": 327.39,
    "low": 326.9867,
    "close": 327.295,
    "volume": 11180,
    "start": "2025-12-24T15:32:00.000Z",
    "end": "2025-12-24T15:33:00.000Z"
  },
  {
    "symbol": "UNH",
    "timeframe": "1m",
    "open": 327.315,
    "high": 327.43,
    "low": 327.24,
    "close": 327.305,
    "volume": 7416,
    "start": "2025-12-24T15:33:00.000Z",
    "end": "2025-12-24T15:34:00.000Z"
  },
  {
    "symbol": "UNH",
    "timeframe": "1m",
    "open": 327.305,
    "high": 327.33,
    "low": 326.8862,
    "close": 327.1,
    "volume": 8722,
    "start": "2025-12-24T15:34:00.000Z",
    "end": "2025-12-24T15:35:00.000Z"
  },
  {
    "symbol": "UNH",
    "timeframe": "1m",
    "open": 327.02,
    "high": 327.19,
    "low": 326.9601,
    "close": 327.04,
    "volume": 5990,
    "start": "2025-12-24T15:35:00.000Z",
    "end": "2025-12-24T15:36:00.000Z"
  },
  {
    "symbol": "UNH",
    "timeframe": "1m",
    "open": 327.04,
    "high": 327.0496,
    "low": 326.8417,
    "close": 326.895,
    "volume": 3795,
    "start": "2025-12-24T15:36:00.000Z",
    "end": "2025-12-24T15:37:00.000Z"
  },
  {
    "symbol": "UNH",
    "timeframe": "1m",
    "open": 326.895,
    "high": 327.3714,
    "low": 326.895,
    "close": 327.26,
    "volume": 41965,
    "start": "2025-12-24T15:37:00.000Z",
    "end": "2025-12-24T15:38:00.000Z"
  },
  {
    "symbol": "UNH",
    "timeframe": "1m",
    "open": 327.26,
    "high": 327.26,
    "low": 326.97,
    "close": 326.99,
    "volume": 6090,
    "start": "2025-12-24T15:38:00.000Z",
    "end": "2025-12-24T15:39:00.000Z"
  },
  {
    "symbol": "UNH",
    "timeframe": "1m",
    "open": 326.9,
    "high": 326.9638,
    "low": 326.57,
    "close": 326.72,
    "volume": 6872,
    "start": "2025-12-24T15:39:00.000Z",
    "end": "2025-12-24T15:40:00.000Z"
  },
  {
    "symbol": "UNH",
    "timeframe": "1m",
    "open": 326.685,
    "high": 326.7499,
    "low": 326.5,
    "close": 326.7499,
    "volume": 8643,
    "start": "2025-12-24T15:40:00.000Z",
    "end": "2025-12-24T15:41:00.000Z"
  },
  {
    "symbol": "UNH",
    "timeframe": "1m",
    "open": 326.7,
    "high": 326.8553,
    "low": 326.595,
    "close": 326.8511,
    "volume": 8424,
    "start": "2025-12-24T15:41:00.000Z",
    "end": "2025-12-24T15:42:00.000Z"
  },
  {
    "symbol": "UNH",
    "timeframe": "1m",
    "open": 326.75,
    "high": 326.8976,
    "low": 326.68,
    "close": 326.69,
    "volume": 3825,
    "start": "2025-12-24T15:42:00.000Z",
    "end": "2025-12-24T15:43:00.000Z"
  },
  {
    "symbol": "UNH",
    "timeframe": "1m",
    "open": 326.64,
    "high": 326.74,
    "low": 326.4,
    "close": 326.4,
    "volume": 10639,
    "start": "2025-12-24T15:43:00.000Z",
    "end": "2025-12-24T15:44:00.000Z"
  },
  {
    "symbol": "UNH",
    "timeframe": "1m",
    "open": 326.4,
    "high": 326.5882,
    "low": 326.375,
    "close": 326.56,
    "volume": 4534,
    "start": "2025-12-24T15:44:00.000Z",
    "end": "2025-12-24T15:45:00.000Z"
  },
  {
    "symbol": "UNH",
    "timeframe": "1m",
    "open": 326.5697,
    "high": 326.6582,
    "low": 326.42,
    "close": 326.42,
    "volume": 4298,
    "start": "2025-12-24T15:45:00.000Z",
    "end": "2025-12-24T15:46:00.000Z"
  },
  {
    "symbol": "UNH",
    "timeframe": "1m",
    "open": 326.25,
    "high": 326.425,
    "low": 326.16,
    "close": 326.36,
    "volume": 5721,
    "start": "2025-12-24T15:46:00.000Z",
    "end": "2025-12-24T15:47:00.000Z"
  },
  {
    "symbol": "UNH",
    "timeframe": "1m",
    "open": 326.36,
    "high": 326.525,
    "low": 326.31,
    "close": 326.525,
    "volume": 4776,
    "start": "2025-12-24T15:47:00.000Z",
    "end": "2025-12-24T15:48:00.000Z"
  },
  {
    "symbol": "UNH",
    "timeframe": "1m",
    "open": 326.5251,
    "high": 326.71,
    "low": 326.44,
    "close": 326.584,
    "volume": 10962,
    "start": "2025-12-24T15:48:00.000Z",
    "end": "2025-12-24T15:49:00.000Z"
  },
  {
    "symbol": "UNH",
    "timeframe": "1m",
    "open": 326.55,
    "high": 326.5845,
    "low": 326.34,
    "close": 326.39,
    "volume": 4431,
    "start": "2025-12-24T15:49:00.000Z",
    "end": "2025-12-24T15:50:00.000Z"
  },
  {
    "symbol": "UNH",
    "timeframe": "1m",
    "open": 326.3,
    "high": 326.54,
    "low": 326.3,
    "close": 326.52,
    "volume": 4332,
    "start": "2025-12-24T15:50:00.000Z",
    "end": "2025-12-24T15:51:00.000Z"
  },
  {
    "symbol": "UNH",
    "timeframe": "1m",
    "open": 326.5,
    "high": 326.6799,
    "low": 326.46,
    "close": 326.6799,
    "volume": 248966,
    "start": "2025-12-24T15:51:00.000Z",
    "end": "2025-12-24T15:52:00.000Z"
  },
  {
    "symbol": "UNH",
    "timeframe": "1m",
    "open": 326.645,
    "high": 326.71,
    "low": 326.51,
    "close": 326.665,
    "volume": 6111,
    "start": "2025-12-24T15:52:00.000Z",
    "end": "2025-12-24T15:53:00.000Z"
  },
  {
    "symbol": "UNH",
    "timeframe": "1m",
    "open": 326.667,
    "high": 326.916,
    "low": 326.667,
    "close": 326.91,
    "volume": 7190,
    "start": "2025-12-24T15:53:00.000Z",
    "end": "2025-12-24T15:54:00.000Z"
  },
  {
    "symbol": "UNH",
    "timeframe": "1m",
    "open": 326.9899,
    "high": 327.11,
    "low": 326.85,
    "close": 326.895,
    "volume": 13220,
    "start": "2025-12-24T15:54:00.000Z",
    "end": "2025-12-24T15:55:00.000Z"
  },
  {
    "symbol": "UNH",
    "timeframe": "1m",
    "open": 326.84,
    "high": 326.9,
    "low": 326.77,
    "close": 326.8731,
    "volume": 4289,
    "start": "2025-12-24T15:55:00.000Z",
    "end": "2025-12-24T15:56:00.000Z"
  },
  {
    "symbol": "UNH",
    "timeframe": "1m",
    "open": 326.86,
    "high": 327.0375,
    "low": 326.77,
    "close": 327,
    "volume": 6495,
    "start": "2025-12-24T15:56:00.000Z",
    "end": "2025-12-24T15:57:00.000Z"
  },
  {
    "symbol": "UNH",
    "timeframe": "1m",
    "open": 326.98,
    "high": 327.27,
    "low": 326.98,
    "close": 327.144,
    "volume": 4313,
    "start": "2025-12-24T15:57:00.000Z",
    "end": "2025-12-24T15:58:00.000Z"
  },
  {
    "symbol": "UNH",
    "timeframe": "1m",
    "open": 327.1651,
    "high": 327.1651,
    "low": 326.95,
    "close": 327.07,
    "volume": 3932,
    "start": "2025-12-24T15:58:00.000Z",
    "end": "2025-12-24T15:59:00.000Z"
  },
  {
    "symbol": "UNH",
    "timeframe": "1m",
    "open": 327.1,
    "high": 327.22,
    "low": 327.08,
    "close": 327.2,
    "volume": 3710,
    "start": "2025-12-24T15:59:00.000Z",
    "end": "2025-12-24T16:00:00.000Z"
  },
  {
    "symbol": "UNH",
    "timeframe": "1m",
    "open": 327.2,
    "high": 327.36,
    "low": 327.19,
    "close": 327.2,
    "volume": 39006,
    "start": "2025-12-24T16:00:00.000Z",
    "end": "2025-12-24T16:01:00.000Z"
  },
  {
    "symbol": "UNH",
    "timeframe": "1m",
    "open": 327.16,
    "high": 327.18,
    "low": 327.06,
    "close": 327.125,
    "volume": 2252,
    "start": "2025-12-24T16:01:00.000Z",
    "end": "2025-12-24T16:02:00.000Z"
  },
  {
    "symbol": "UNH",
    "timeframe": "1m",
    "open": 327.1189,
    "high": 327.25,
    "low": 327.04,
    "close": 327.185,
    "volume": 4567,
    "start": "2025-12-24T16:02:00.000Z",
    "end": "2025-12-24T16:03:00.000Z"
  },
  {
    "symbol": "UNH",
    "timeframe": "1m",
    "open": 327.185,
    "high": 327.25,
    "low": 327.09,
    "close": 327.13,
    "volume": 10346,
    "start": "2025-12-24T16:03:00.000Z",
    "end": "2025-12-24T16:04:00.000Z"
  },
  {
    "symbol": "UNH",
    "timeframe": "1m",
    "open": 327.175,
    "high": 327.175,
    "low": 326.99,
    "close": 326.9915,
    "volume": 3522,
    "start": "2025-12-24T16:04:00.000Z",
    "end": "2025-12-24T16:05:00.000Z"
  },
  {
    "symbol": "UNH",
    "timeframe": "1m",
    "open": 326.9904,
    "high": 326.991,
    "low": 326.82,
    "close": 326.93,
    "volume": 10381,
    "start": "2025-12-24T16:05:00.000Z",
    "end": "2025-12-24T16:06:00.000Z"
  },
  {
    "symbol": "UNH",
    "timeframe": "1m",
    "open": 326.855,
    "high": 327,
    "low": 326.855,
    "close": 326.955,
    "volume": 3335,
    "start": "2025-12-24T16:06:00.000Z",
    "end": "2025-12-24T16:07:00.000Z"
  },
  {
    "symbol": "UNH",
    "timeframe": "1m",
    "open": 326.91,
    "high": 327.07,
    "low": 326.8597,
    "close": 327,
    "volume": 4338,
    "start": "2025-12-24T16:07:00.000Z",
    "end": "2025-12-24T16:08:00.000Z"
  },
  {
    "symbol": "UNH",
    "timeframe": "1m",
    "open": 327.15,
    "high": 327.31,
    "low": 327.11,
    "close": 327.31,
    "volume": 8088,
    "start": "2025-12-24T16:08:00.000Z",
    "end": "2025-12-24T16:09:00.000Z"
  },
  {
    "symbol": "UNH",
    "timeframe": "1m",
    "open": 327.328,
    "high": 327.328,
    "low": 326.94,
    "close": 326.95,
    "volume": 5285,
    "start": "2025-12-24T16:09:00.000Z",
    "end": "2025-12-24T16:10:00.000Z"
  },
  {
    "symbol": "UNH",
    "timeframe": "1m",
    "open": 327.04,
    "high": 327.075,
    "low": 326.8118,
    "close": 326.87,
    "volume": 3046,
    "start": "2025-12-24T16:10:00.000Z",
    "end": "2025-12-24T16:11:00.000Z"
  },
  {
    "symbol": "UNH",
    "timeframe": "1m",
    "open": 326.87,
    "high": 327.24,
    "low": 326.8401,
    "close": 327.24,
    "volume": 11231,
    "start": "2025-12-24T16:11:00.000Z",
    "end": "2025-12-24T16:12:00.000Z"
  },
  {
    "symbol": "UNH",
    "timeframe": "1m",
    "open": 327.2103,
    "high": 327.45,
    "low": 327.11,
    "close": 327.3,
    "volume": 15044,
    "start": "2025-12-24T16:12:00.000Z",
    "end": "2025-12-24T16:13:00.000Z"
  },
  {
    "symbol": "UNH",
    "timeframe": "1m",
    "open": 327.03,
    "high": 327.2409,
    "low": 326.9,
    "close": 327.2409,
    "volume": 23111,
    "start": "2025-12-24T16:13:00.000Z",
    "end": "2025-12-24T16:14:00.000Z"
  },
  {
    "symbol": "UNH",
    "timeframe": "1m",
    "open": 327.175,
    "high": 327.2201,
    "low": 327.09,
    "close": 327.22,
    "volume": 2072,
    "start": "2025-12-24T16:14:00.000Z",
    "end": "2025-12-24T16:15:00.000Z"
  },
  {
    "symbol": "UNH",
    "timeframe": "1m",
    "open": 327.22,
    "high": 327.225,
    "low": 327.12,
    "close": 327.12,
    "volume": 5660,
    "start": "2025-12-24T16:15:00.000Z",
    "end": "2025-12-24T16:16:00.000Z"
  },
  {
    "symbol": "UNH",
    "timeframe": "1m",
    "open": 327.185,
    "high": 327.3,
    "low": 327.1401,
    "close": 327.27,
    "volume": 7853,
    "start": "2025-12-24T16:16:00.000Z",
    "end": "2025-12-24T16:17:00.000Z"
  },
  {
    "symbol": "UNH",
    "timeframe": "1m",
    "open": 327.2465,
    "high": 327.34,
    "low": 327.18,
    "close": 327.24,
    "volume": 2941,
    "start": "2025-12-24T16:17:00.000Z",
    "end": "2025-12-24T16:18:00.000Z"
  },
  {
    "symbol": "UNH",
    "timeframe": "1m",
    "open": 327.225,
    "high": 327.4,
    "low": 327.2,
    "close": 327.335,
    "volume": 10991,
    "start": "2025-12-24T16:18:00.000Z",
    "end": "2025-12-24T16:19:00.000Z"
  },
  {
    "symbol": "UNH",
    "timeframe": "1m",
    "open": 327.335,
    "high": 327.71,
    "low": 327.335,
    "close": 327.585,
    "volume": 17390,
    "start": "2025-12-24T16:19:00.000Z",
    "end": "2025-12-24T16:20:00.000Z"
  },
  {
    "symbol": "UNH",
    "timeframe": "1m",
    "open": 327.585,
    "high": 327.95,
    "low": 327.53,
    "close": 327.885,
    "volume": 14578,
    "start": "2025-12-24T16:20:00.000Z",
    "end": "2025-12-24T16:21:00.000Z"
  },
  {
    "symbol": "UNH",
    "timeframe": "1m",
    "open": 327.82,
    "high": 327.855,
    "low": 327.55,
    "close": 327.55,
    "volume": 5337,
    "start": "2025-12-24T16:21:00.000Z",
    "end": "2025-12-24T16:22:00.000Z"
  },
  {
    "symbol": "UNH",
    "timeframe": "1m",
    "open": 327.62,
    "high": 327.85,
    "low": 327.521,
    "close": 327.6441,
    "volume": 7395,
    "start": "2025-12-24T16:22:00.000Z",
    "end": "2025-12-24T16:23:00.000Z"
  },
  {
    "symbol": "UNH",
    "timeframe": "1m",
    "open": 327.635,
    "high": 327.8391,
    "low": 327.57,
    "close": 327.7,
    "volume": 7649,
    "start": "2025-12-24T16:23:00.000Z",
    "end": "2025-12-24T16:24:00.000Z"
  },
  {
    "symbol": "UNH",
    "timeframe": "1m",
    "open": 327.705,
    "high": 327.7499,
    "low": 327.61,
    "close": 327.68,
    "volume": 4036,
    "start": "2025-12-24T16:24:00.000Z",
    "end": "2025-12-24T16:25:00.000Z"
  },
  {
    "symbol": "UNH",
    "timeframe": "1m",
    "open": 327.61,
    "high": 327.68,
    "low": 327.49,
    "close": 327.53,
    "volume": 6933,
    "start": "2025-12-24T16:25:00.000Z",
    "end": "2025-12-24T16:26:00.000Z"
  },
  {
    "symbol": "UNH",
    "timeframe": "1m",
    "open": 327.5,
    "high": 327.55,
    "low": 327.16,
    "close": 327.255,
    "volume": 10899,
    "start": "2025-12-24T16:26:00.000Z",
    "end": "2025-12-24T16:27:00.000Z"
  },
  {
    "symbol": "UNH",
    "timeframe": "1m",
    "open": 327.25,
    "high": 327.485,
    "low": 327.21,
    "close": 327.485,
    "volume": 14265,
    "start": "2025-12-24T16:27:00.000Z",
    "end": "2025-12-24T16:28:00.000Z"
  },
  {
    "symbol": "UNH",
    "timeframe": "1m",
    "open": 327.4688,
    "high": 327.55,
    "low": 327.44,
    "close": 327.45,
    "volume": 4718,
    "start": "2025-12-24T16:28:00.000Z",
    "end": "2025-12-24T16:29:00.000Z"
  },
  {
    "symbol": "UNH",
    "timeframe": "1m",
    "open": 327.385,
    "high": 327.46,
    "low": 327.3214,
    "close": 327.445,
    "volume": 2818,
    "start": "2025-12-24T16:29:00.000Z",
    "end": "2025-12-24T16:30:00.000Z"
  },
  {
    "symbol": "UNH",
    "timeframe": "1m",
    "open": 327.3804,
    "high": 327.4076,
    "low": 327.29,
    "close": 327.3,
    "volume": 4255,
    "start": "2025-12-24T16:30:00.000Z",
    "end": "2025-12-24T16:31:00.000Z"
  },
  {
    "symbol": "UNH",
    "timeframe": "1m",
    "open": 327.315,
    "high": 327.3485,
    "low": 327.16,
    "close": 327.185,
    "volume": 3510,
    "start": "2025-12-24T16:31:00.000Z",
    "end": "2025-12-24T16:32:00.000Z"
  },
  {
    "symbol": "UNH",
    "timeframe": "1m",
    "open": 327.15,
    "high": 327.18,
    "low": 327,
    "close": 327.1,
    "volume": 5176,
    "start": "2025-12-24T16:32:00.000Z",
    "end": "2025-12-24T16:33:00.000Z"
  },
  {
    "symbol": "UNH",
    "timeframe": "1m",
    "open": 327.0763,
    "high": 327.1054,
    "low": 326.98,
    "close": 327.1,
    "volume": 4202,
    "start": "2025-12-24T16:33:00.000Z",
    "end": "2025-12-24T16:34:00.000Z"
  },
  {
    "symbol": "UNH",
    "timeframe": "1m",
    "open": 327.1,
    "high": 327.355,
    "low": 327.1,
    "close": 327.355,
    "volume": 2960,
    "start": "2025-12-24T16:34:00.000Z",
    "end": "2025-12-24T16:35:00.000Z"
  },
  {
    "symbol": "UNH",
    "timeframe": "1m",
    "open": 327.3431,
    "high": 327.619,
    "low": 327.3,
    "close": 327.5575,
    "volume": 6130,
    "start": "2025-12-24T16:35:00.000Z",
    "end": "2025-12-24T16:36:00.000Z"
  },
  {
    "symbol": "UNH",
    "timeframe": "1m",
    "open": 327.57,
    "high": 327.65,
    "low": 327.5,
    "close": 327.57,
    "volume": 4685,
    "start": "2025-12-24T16:36:00.000Z",
    "end": "2025-12-24T16:37:00.000Z"
  },
  {
    "symbol": "UNH",
    "timeframe": "1m",
    "open": 327.52,
    "high": 327.6742,
    "low": 327.51,
    "close": 327.6742,
    "volume": 4436,
    "start": "2025-12-24T16:37:00.000Z",
    "end": "2025-12-24T16:38:00.000Z"
  },
  {
    "symbol": "UNH",
    "timeframe": "1m",
    "open": 327.63,
    "high": 327.79,
    "low": 327.58,
    "close": 327.79,
    "volume": 8041,
    "start": "2025-12-24T16:38:00.000Z",
    "end": "2025-12-24T16:39:00.000Z"
  },
  {
    "symbol": "UNH",
    "timeframe": "1m",
    "open": 327.72,
    "high": 327.88,
    "low": 327.7048,
    "close": 327.8,
    "volume": 5028,
    "start": "2025-12-24T16:39:00.000Z",
    "end": "2025-12-24T16:40:00.000Z"
  },
  {
    "symbol": "UNH",
    "timeframe": "1m",
    "open": 327.87,
    "high": 327.95,
    "low": 327.83,
    "close": 327.86,
    "volume": 7173,
    "start": "2025-12-24T16:40:00.000Z",
    "end": "2025-12-24T16:41:00.000Z"
  },
  {
    "symbol": "UNH",
    "timeframe": "1m",
    "open": 327.88,
    "high": 327.88,
    "low": 327.7,
    "close": 327.8221,
    "volume": 3419,
    "start": "2025-12-24T16:41:00.000Z",
    "end": "2025-12-24T16:42:00.000Z"
  },
  {
    "symbol": "UNH",
    "timeframe": "1m",
    "open": 327.8195,
    "high": 327.834,
    "low": 327.638,
    "close": 327.665,
    "volume": 2263,
    "start": "2025-12-24T16:42:00.000Z",
    "end": "2025-12-24T16:43:00.000Z"
  },
  {
    "symbol": "UNH",
    "timeframe": "1m",
    "open": 327.73,
    "high": 327.9,
    "low": 327.71,
    "close": 327.725,
    "volume": 8268,
    "start": "2025-12-24T16:43:00.000Z",
    "end": "2025-12-24T16:44:00.000Z"
  },
  {
    "symbol": "UNH",
    "timeframe": "1m",
    "open": 327.79,
    "high": 327.8,
    "low": 327.6756,
    "close": 327.8,
    "volume": 3137,
    "start": "2025-12-24T16:44:00.000Z",
    "end": "2025-12-24T16:45:00.000Z"
  },
  {
    "symbol": "UNH",
    "timeframe": "1m",
    "open": 327.7607,
    "high": 327.8899,
    "low": 327.622,
    "close": 327.622,
    "volume": 4738,
    "start": "2025-12-24T16:45:00.000Z",
    "end": "2025-12-24T16:46:00.000Z"
  },
  {
    "symbol": "UNH",
    "timeframe": "1m",
    "open": 327.64,
    "high": 327.735,
    "low": 327.64,
    "close": 327.7091,
    "volume": 3524,
    "start": "2025-12-24T16:46:00.000Z",
    "end": "2025-12-24T16:47:00.000Z"
  },
  {
    "symbol": "UNH",
    "timeframe": "1m",
    "open": 327.7399,
    "high": 327.7399,
    "low": 327.3901,
    "close": 327.3901,
    "volume": 5944,
    "start": "2025-12-24T16:47:00.000Z",
    "end": "2025-12-24T16:48:00.000Z"
  },
  {
    "symbol": "UNH",
    "timeframe": "1m",
    "open": 327.38,
    "high": 327.6,
    "low": 327.36,
    "close": 327.5785,
    "volume": 5119,
    "start": "2025-12-24T16:48:00.000Z",
    "end": "2025-12-24T16:49:00.000Z"
  },
  {
    "symbol": "UNH",
    "timeframe": "1m",
    "open": 327.565,
    "high": 327.565,
    "low": 327.1116,
    "close": 327.32,
    "volume": 12023,
    "start": "2025-12-24T16:49:00.000Z",
    "end": "2025-12-24T16:50:00.000Z"
  },
  {
    "symbol": "UNH",
    "timeframe": "1m",
    "open": 327.324,
    "high": 327.324,
    "low": 327.12,
    "close": 327.16,
    "volume": 2534,
    "start": "2025-12-24T16:50:00.000Z",
    "end": "2025-12-24T16:51:00.000Z"
  },
  {
    "symbol": "UNH",
    "timeframe": "1m",
    "open": 327.16,
    "high": 327.285,
    "low": 327.12,
    "close": 327.285,
    "volume": 5358,
    "start": "2025-12-24T16:51:00.000Z",
    "end": "2025-12-24T16:52:00.000Z"
  },
  {
    "symbol": "UNH",
    "timeframe": "1m",
    "open": 327.23,
    "high": 327.3299,
    "low": 327.11,
    "close": 327.11,
    "volume": 6830,
    "start": "2025-12-24T16:52:00.000Z",
    "end": "2025-12-24T16:53:00.000Z"
  },
  {
    "symbol": "UNH",
    "timeframe": "1m",
    "open": 327.09,
    "high": 327.155,
    "low": 326.76,
    "close": 326.89,
    "volume": 4314,
    "start": "2025-12-24T16:53:00.000Z",
    "end": "2025-12-24T16:54:00.000Z"
  },
  {
    "symbol": "UNH",
    "timeframe": "1m",
    "open": 326.91,
    "high": 327.25,
    "low": 326.85,
    "close": 327.25,
    "volume": 5366,
    "start": "2025-12-24T16:54:00.000Z",
    "end": "2025-12-24T16:55:00.000Z"
  },
  {
    "symbol": "UNH",
    "timeframe": "1m",
    "open": 327.3,
    "high": 327.5,
    "low": 327.1555,
    "close": 327.465,
    "volume": 8466,
    "start": "2025-12-24T16:55:00.000Z",
    "end": "2025-12-24T16:56:00.000Z"
  },
  {
    "symbol": "UNH",
    "timeframe": "1m",
    "open": 327.465,
    "high": 327.62,
    "low": 327.46,
    "close": 327.585,
    "volume": 8261,
    "start": "2025-12-24T16:56:00.000Z",
    "end": "2025-12-24T16:57:00.000Z"
  },
  {
    "symbol": "UNH",
    "timeframe": "1m",
    "open": 327.61,
    "high": 327.705,
    "low": 327.52,
    "close": 327.5382,
    "volume": 10736,
    "start": "2025-12-24T16:57:00.000Z",
    "end": "2025-12-24T16:58:00.000Z"
  },
  {
    "symbol": "UNH",
    "timeframe": "1m",
    "open": 327.5456,
    "high": 327.825,
    "low": 327.5456,
    "close": 327.825,
    "volume": 6857,
    "start": "2025-12-24T16:58:00.000Z",
    "end": "2025-12-24T16:59:00.000Z"
  },
  {
    "symbol": "UNH",
    "timeframe": "1m",
    "open": 327.86,
    "high": 328.12,
    "low": 327.77,
    "close": 328.06,
    "volume": 24507,
    "start": "2025-12-24T16:59:00.000Z",
    "end": "2025-12-24T17:00:00.000Z"
  },
  {
    "symbol": "UNH",
    "timeframe": "1m",
    "open": 328.06,
    "high": 328.13,
    "low": 327.835,
    "close": 327.9,
    "volume": 8945,
    "start": "2025-12-24T17:00:00.000Z",
    "end": "2025-12-24T17:01:00.000Z"
  },
  {
    "symbol": "UNH",
    "timeframe": "1m",
    "open": 327.9,
    "high": 328,
    "low": 327.83,
    "close": 327.99,
    "volume": 6357,
    "start": "2025-12-24T17:01:00.000Z",
    "end": "2025-12-24T17:02:00.000Z"
  },
  {
    "symbol": "UNH",
    "timeframe": "1m",
    "open": 327.925,
    "high": 328.13,
    "low": 327.8836,
    "close": 328.12,
    "volume": 7184,
    "start": "2025-12-24T17:02:00.000Z",
    "end": "2025-12-24T17:03:00.000Z"
  },
  {
    "symbol": "UNH",
    "timeframe": "1m",
    "open": 328.0233,
    "high": 328.51,
    "low": 328.011,
    "close": 328.48,
    "volume": 14552,
    "start": "2025-12-24T17:03:00.000Z",
    "end": "2025-12-24T17:04:00.000Z"
  },
  {
    "symbol": "UNH",
    "timeframe": "1m",
    "open": 328.49,
    "high": 328.73,
    "low": 328.46,
    "close": 328.55,
    "volume": 24433,
    "start": "2025-12-24T17:04:00.000Z",
    "end": "2025-12-24T17:05:00.000Z"
  },
  {
    "symbol": "UNH",
    "timeframe": "1m",
    "open": 328.5401,
    "high": 328.66,
    "low": 328.43,
    "close": 328.66,
    "volume": 7237,
    "start": "2025-12-24T17:05:00.000Z",
    "end": "2025-12-24T17:06:00.000Z"
  },
  {
    "symbol": "UNH",
    "timeframe": "1m",
    "open": 328.7,
    "high": 328.705,
    "low": 328.43,
    "close": 328.565,
    "volume": 8685,
    "start": "2025-12-24T17:06:00.000Z",
    "end": "2025-12-24T17:07:00.000Z"
  },
  {
    "symbol": "UNH",
    "timeframe": "1m",
    "open": 328.5013,
    "high": 328.67,
    "low": 328.45,
    "close": 328.67,
    "volume": 7402,
    "start": "2025-12-24T17:07:00.000Z",
    "end": "2025-12-24T17:08:00.000Z"
  },
  {
    "symbol": "UNH",
    "timeframe": "1m",
    "open": 328.63,
    "high": 328.74,
    "low": 328.57,
    "close": 328.58,
    "volume": 12327,
    "start": "2025-12-24T17:08:00.000Z",
    "end": "2025-12-24T17:09:00.000Z"
  },
  {
    "symbol": "UNH",
    "timeframe": "1m",
    "open": 328.55,
    "high": 328.67,
    "low": 328.3024,
    "close": 328.67,
    "volume": 6772,
    "start": "2025-12-24T17:09:00.000Z",
    "end": "2025-12-24T17:10:00.000Z"
  },
  {
    "symbol": "UNH",
    "timeframe": "1m",
    "open": 328.5889,
    "high": 328.708,
    "low": 328.5889,
    "close": 328.68,
    "volume": 6991,
    "start": "2025-12-24T17:10:00.000Z",
    "end": "2025-12-24T17:11:00.000Z"
  },
  {
    "symbol": "UNH",
    "timeframe": "1m",
    "open": 328.66,
    "high": 328.9,
    "low": 328.63,
    "close": 328.835,
    "volume": 16732,
    "start": "2025-12-24T17:11:00.000Z",
    "end": "2025-12-24T17:12:00.000Z"
  },
  {
    "symbol": "UNH",
    "timeframe": "1m",
    "open": 328.8164,
    "high": 328.99,
    "low": 328.5899,
    "close": 328.67,
    "volume": 16601,
    "start": "2025-12-24T17:12:00.000Z",
    "end": "2025-12-24T17:13:00.000Z"
  },
  {
    "symbol": "UNH",
    "timeframe": "1m",
    "open": 328.65,
    "high": 328.655,
    "low": 328.51,
    "close": 328.55,
    "volume": 8072,
    "start": "2025-12-24T17:13:00.000Z",
    "end": "2025-12-24T17:14:00.000Z"
  },
  {
    "symbol": "UNH",
    "timeframe": "1m",
    "open": 328.575,
    "high": 328.7999,
    "low": 328.46,
    "close": 328.53,
    "volume": 7367,
    "start": "2025-12-24T17:14:00.000Z",
    "end": "2025-12-24T17:15:00.000Z"
  },
  {
    "symbol": "UNH",
    "timeframe": "1m",
    "open": 328.53,
    "high": 328.549,
    "low": 328.41,
    "close": 328.45,
    "volume": 7901,
    "start": "2025-12-24T17:15:00.000Z",
    "end": "2025-12-24T17:16:00.000Z"
  },
  {
    "symbol": "UNH",
    "timeframe": "1m",
    "open": 328.44,
    "high": 328.48,
    "low": 328.2001,
    "close": 328.285,
    "volume": 3460,
    "start": "2025-12-24T17:16:00.000Z",
    "end": "2025-12-24T17:17:00.000Z"
  },
  {
    "symbol": "UNH",
    "timeframe": "1m",
    "open": 328.2731,
    "high": 328.285,
    "low": 328.1101,
    "close": 328.225,
    "volume": 8048,
    "start": "2025-12-24T17:17:00.000Z",
    "end": "2025-12-24T17:18:00.000Z"
  },
  {
    "symbol": "UNH",
    "timeframe": "1m",
    "open": 328.2042,
    "high": 328.26,
    "low": 328.14,
    "close": 328.15,
    "volume": 6469,
    "start": "2025-12-24T17:18:00.000Z",
    "end": "2025-12-24T17:19:00.000Z"
  },
  {
    "symbol": "UNH",
    "timeframe": "1m",
    "open": 328.173,
    "high": 328.2,
    "low": 328.0618,
    "close": 328.106,
    "volume": 10757,
    "start": "2025-12-24T17:19:00.000Z",
    "end": "2025-12-24T17:20:00.000Z"
  },
  {
    "symbol": "UNH",
    "timeframe": "1m",
    "open": 328.11,
    "high": 328.3,
    "low": 328.08,
    "close": 328.0813,
    "volume": 2462,
    "start": "2025-12-24T17:20:00.000Z",
    "end": "2025-12-24T17:21:00.000Z"
  },
  {
    "symbol": "UNH",
    "timeframe": "1m",
    "open": 328.1575,
    "high": 328.1899,
    "low": 327.98,
    "close": 328.1087,
    "volume": 6414,
    "start": "2025-12-24T17:21:00.000Z",
    "end": "2025-12-24T17:22:00.000Z"
  },
  {
    "symbol": "UNH",
    "timeframe": "1m",
    "open": 328.06,
    "high": 328.28,
    "low": 328.0591,
    "close": 328.165,
    "volume": 5763,
    "start": "2025-12-24T17:22:00.000Z",
    "end": "2025-12-24T17:23:00.000Z"
  },
  {
    "symbol": "UNH",
    "timeframe": "1m",
    "open": 328.154,
    "high": 328.2269,
    "low": 328.11,
    "close": 328.16,
    "volume": 2177,
    "start": "2025-12-24T17:23:00.000Z",
    "end": "2025-12-24T17:24:00.000Z"
  },
  {
    "symbol": "UNH",
    "timeframe": "1m",
    "open": 328.16,
    "high": 328.163,
    "low": 328.04,
    "close": 328.04,
    "volume": 8725,
    "start": "2025-12-24T17:24:00.000Z",
    "end": "2025-12-24T17:25:00.000Z"
  },
  {
    "symbol": "UNH",
    "timeframe": "1m",
    "open": 328.03,
    "high": 328.21,
    "low": 327.995,
    "close": 328.1091,
    "volume": 5169,
    "start": "2025-12-24T17:25:00.000Z",
    "end": "2025-12-24T17:26:00.000Z"
  },
  {
    "symbol": "UNH",
    "timeframe": "1m",
    "open": 328.14,
    "high": 328.14,
    "low": 328,
    "close": 328,
    "volume": 3056,
    "start": "2025-12-24T17:26:00.000Z",
    "end": "2025-12-24T17:27:00.000Z"
  },
  {
    "symbol": "UNH",
    "timeframe": "1m",
    "open": 327.97,
    "high": 328.11,
    "low": 327.88,
    "close": 328.11,
    "volume": 10204,
    "start": "2025-12-24T17:27:00.000Z",
    "end": "2025-12-24T17:28:00.000Z"
  },
  {
    "symbol": "UNH",
    "timeframe": "1m",
    "open": 328.04,
    "high": 328.26,
    "low": 328.04,
    "close": 328.26,
    "volume": 5222,
    "start": "2025-12-24T17:28:00.000Z",
    "end": "2025-12-24T17:29:00.000Z"
  },
  {
    "symbol": "UNH",
    "timeframe": "1m",
    "open": 328.28,
    "high": 328.4049,
    "low": 328.24,
    "close": 328.25,
    "volume": 4512,
    "start": "2025-12-24T17:29:00.000Z",
    "end": "2025-12-24T17:30:00.000Z"
  },
  {
    "symbol": "UNH",
    "timeframe": "1m",
    "open": 328.24,
    "high": 328.2831,
    "low": 328.16,
    "close": 328.18,
    "volume": 4897,
    "start": "2025-12-24T17:30:00.000Z",
    "end": "2025-12-24T17:31:00.000Z"
  },
  {
    "symbol": "UNH",
    "timeframe": "1m",
    "open": 328.2,
    "high": 328.25,
    "low": 328.12,
    "close": 328.1601,
    "volume": 3672,
    "start": "2025-12-24T17:31:00.000Z",
    "end": "2025-12-24T17:32:00.000Z"
  },
  {
    "symbol": "UNH",
    "timeframe": "1m",
    "open": 328.25,
    "high": 328.4681,
    "low": 328.1701,
    "close": 328.4681,
    "volume": 9888,
    "start": "2025-12-24T17:32:00.000Z",
    "end": "2025-12-24T17:33:00.000Z"
  },
  {
    "symbol": "UNH",
    "timeframe": "1m",
    "open": 328.4782,
    "high": 328.51,
    "low": 328.4101,
    "close": 328.43,
    "volume": 7879,
    "start": "2025-12-24T17:33:00.000Z",
    "end": "2025-12-24T17:34:00.000Z"
  },
  {
    "symbol": "UNH",
    "timeframe": "1m",
    "open": 328.42,
    "high": 328.53,
    "low": 328.38,
    "close": 328.5025,
    "volume": 8121,
    "start": "2025-12-24T17:34:00.000Z",
    "end": "2025-12-24T17:35:00.000Z"
  },
  {
    "symbol": "UNH",
    "timeframe": "1m",
    "open": 328.42,
    "high": 328.51,
    "low": 328.41,
    "close": 328.4201,
    "volume": 4538,
    "start": "2025-12-24T17:35:00.000Z",
    "end": "2025-12-24T17:36:00.000Z"
  },
  {
    "symbol": "UNH",
    "timeframe": "1m",
    "open": 328.42,
    "high": 328.43,
    "low": 328.34,
    "close": 328.43,
    "volume": 4112,
    "start": "2025-12-24T17:36:00.000Z",
    "end": "2025-12-24T17:37:00.000Z"
  },
  {
    "symbol": "UNH",
    "timeframe": "1m",
    "open": 328.46,
    "high": 328.46,
    "low": 328.23,
    "close": 328.3312,
    "volume": 5555,
    "start": "2025-12-24T17:37:00.000Z",
    "end": "2025-12-24T17:38:00.000Z"
  },
  {
    "symbol": "UNH",
    "timeframe": "1m",
    "open": 328.3547,
    "high": 328.36,
    "low": 328.235,
    "close": 328.36,
    "volume": 4832,
    "start": "2025-12-24T17:38:00.000Z",
    "end": "2025-12-24T17:39:00.000Z"
  },
  {
    "symbol": "UNH",
    "timeframe": "1m",
    "open": 328.365,
    "high": 328.48,
    "low": 328.31,
    "close": 328.35,
    "volume": 6838,
    "start": "2025-12-24T17:39:00.000Z",
    "end": "2025-12-24T17:40:00.000Z"
  },
  {
    "symbol": "UNH",
    "timeframe": "1m",
    "open": 328.375,
    "high": 328.44,
    "low": 328.29,
    "close": 328.37,
    "volume": 8628,
    "start": "2025-12-24T17:40:00.000Z",
    "end": "2025-12-24T17:41:00.000Z"
  },
  {
    "symbol": "UNH",
    "timeframe": "1m",
    "open": 328.42,
    "high": 328.42,
    "low": 328.2201,
    "close": 328.28,
    "volume": 5583,
    "start": "2025-12-24T17:41:00.000Z",
    "end": "2025-12-24T17:42:00.000Z"
  },
  {
    "symbol": "UNH",
    "timeframe": "1m",
    "open": 328.23,
    "high": 328.287,
    "low": 328.0001,
    "close": 328.13,
    "volume": 6803,
    "start": "2025-12-24T17:42:00.000Z",
    "end": "2025-12-24T17:43:00.000Z"
  },
  {
    "symbol": "UNH",
    "timeframe": "1m",
    "open": 328.18,
    "high": 328.19,
    "low": 328.0501,
    "close": 328.0851,
    "volume": 3584,
    "start": "2025-12-24T17:43:00.000Z",
    "end": "2025-12-24T17:44:00.000Z"
  },
  {
    "symbol": "UNH",
    "timeframe": "1m",
    "open": 328.1179,
    "high": 328.25,
    "low": 328.01,
    "close": 328.25,
    "volume": 6492,
    "start": "2025-12-24T17:44:00.000Z",
    "end": "2025-12-24T17:45:00.000Z"
  },
  {
    "symbol": "UNH",
    "timeframe": "1m",
    "open": 328.14,
    "high": 328.2,
    "low": 328.08,
    "close": 328.12,
    "volume": 11838,
    "start": "2025-12-24T17:45:00.000Z",
    "end": "2025-12-24T17:46:00.000Z"
  },
  {
    "symbol": "UNH",
    "timeframe": "1m",
    "open": 328.12,
    "high": 328.25,
    "low": 328.1,
    "close": 328.23,
    "volume": 7919,
    "start": "2025-12-24T17:46:00.000Z",
    "end": "2025-12-24T17:47:00.000Z"
  },
  {
    "symbol": "UNH",
    "timeframe": "1m",
    "open": 328.185,
    "high": 328.21,
    "low": 328.12,
    "close": 328.19,
    "volume": 8387,
    "start": "2025-12-24T17:47:00.000Z",
    "end": "2025-12-24T17:48:00.000Z"
  },
  {
    "symbol": "UNH",
    "timeframe": "1m",
    "open": 328.15,
    "high": 328.188911,
    "low": 328.065,
    "close": 328.07,
    "volume": 4569,
    "start": "2025-12-24T17:48:00.000Z",
    "end": "2025-12-24T17:49:00.000Z"
  },
  {
    "symbol": "UNH",
    "timeframe": "1m",
    "open": 328.06,
    "high": 328.06,
    "low": 327.715,
    "close": 327.7501,
    "volume": 7684,
    "start": "2025-12-24T17:49:00.000Z",
    "end": "2025-12-24T17:50:00.000Z"
  },
  {
    "symbol": "UNH",
    "timeframe": "1m",
    "open": 327.79,
    "high": 327.942,
    "low": 327.72,
    "close": 327.7722,
    "volume": 9546,
    "start": "2025-12-24T17:50:00.000Z",
    "end": "2025-12-24T17:51:00.000Z"
  },
  {
    "symbol": "UNH",
    "timeframe": "1m",
    "open": 327.765,
    "high": 327.855,
    "low": 327.67,
    "close": 327.76,
    "volume": 5772,
    "start": "2025-12-24T17:51:00.000Z",
    "end": "2025-12-24T17:52:00.000Z"
  },
  {
    "symbol": "UNH",
    "timeframe": "1m",
    "open": 327.68,
    "high": 327.73,
    "low": 327.54,
    "close": 327.655,
    "volume": 7224,
    "start": "2025-12-24T17:52:00.000Z",
    "end": "2025-12-24T17:53:00.000Z"
  },
  {
    "symbol": "UNH",
    "timeframe": "1m",
    "open": 327.73,
    "high": 327.8645,
    "low": 327.69,
    "close": 327.82,
    "volume": 10749,
    "start": "2025-12-24T17:53:00.000Z",
    "end": "2025-12-24T17:54:00.000Z"
  },
  {
    "symbol": "UNH",
    "timeframe": "1m",
    "open": 327.84,
    "high": 328.0312,
    "low": 327.79,
    "close": 328,
    "volume": 12437,
    "start": "2025-12-24T17:54:00.000Z",
    "end": "2025-12-24T17:55:00.000Z"
  },
  {
    "symbol": "UNH",
    "timeframe": "1m",
    "open": 328.01,
    "high": 328.06,
    "low": 327.7285,
    "close": 327.91,
    "volume": 7655,
    "start": "2025-12-24T17:55:00.000Z",
    "end": "2025-12-24T17:56:00.000Z"
  },
  {
    "symbol": "UNH",
    "timeframe": "1m",
    "open": 327.925,
    "high": 328.1,
    "low": 327.92,
    "close": 328.02,
    "volume": 23257,
    "start": "2025-12-24T17:56:00.000Z",
    "end": "2025-12-24T17:57:00.000Z"
  },
  {
    "symbol": "UNH",
    "timeframe": "1m",
    "open": 328.04,
    "high": 328.04,
    "low": 327.91,
    "close": 327.935,
    "volume": 13707,
    "start": "2025-12-24T17:57:00.000Z",
    "end": "2025-12-24T17:58:00.000Z"
  },
  {
    "symbol": "UNH",
    "timeframe": "1m",
    "open": 327.93,
    "high": 328.15,
    "low": 327.89,
    "close": 327.92,
    "volume": 26011,
    "start": "2025-12-24T17:58:00.000Z",
    "end": "2025-12-24T17:59:00.000Z"
  },
  {
    "symbol": "UNH",
    "timeframe": "1m",
    "open": 327.89,
    "high": 328,
    "low": 327.58,
    "close": 327.8,
    "volume": 31854,
    "start": "2025-12-24T17:59:00.000Z",
    "end": "2025-12-24T18:00:00.000Z"
  },
  {
    "symbol": "UNH",
    "timeframe": "1m",
    "open": 327.58,
    "high": 327.58,
    "low": 327.58,
    "close": 327.58,
    "volume": 263654,
    "start": "2025-12-24T18:00:00.000Z",
    "end": "2025-12-24T18:01:00.000Z"
  },
  {
    "symbol": "UNH",
    "timeframe": "1m",
    "open": 327.05,
    "high": 327.05,
    "low": 327.05,
    "close": 327.05,
    "volume": 103,
    "start": "2025-12-24T21:01:00.000Z",
    "end": "2025-12-24T21:02:00.000Z"
  },
  {
    "symbol": "UNH",
    "timeframe": "1m",
    "open": 327.14,
    "high": 327.14,
    "low": 327.14,
    "close": 327.14,
    "volume": 61,
    "start": "2025-12-24T21:02:00.000Z",
    "end": "2025-12-24T21:03:00.000Z"
  },
  {
    "symbol": "UNH",
    "timeframe": "1m",
    "open": 327.05,
    "high": 327.05,
    "low": 327.05,
    "close": 327.05,
    "volume": 50,
    "start": "2025-12-24T21:30:00.000Z",
    "end": "2025-12-24T21:31:00.000Z"
  },
  {
    "symbol": "UNH",
    "timeframe": "1m",
    "open": 327,
    "high": 327,
    "low": 327,
    "close": 327,
    "volume": 69,
    "start": "2025-12-24T21:44:00.000Z",
    "end": "2025-12-24T21:45:00.000Z"
  },
  {
    "symbol": "UNH",
    "timeframe": "1m",
    "open": 327.01,
    "high": 327.01,
    "low": 327,
    "close": 327,
    "volume": 406,
    "start": "2025-12-24T21:47:00.000Z",
    "end": "2025-12-24T21:48:00.000Z"
  }
]